Workbook

Sheet Introduction
B5: THIS WORKSHEET HAS BEEN PREPARED TO DEVELOP AN UNSECURED RETAIL LENDING
B6: CONTENT OF SAS CREDIT ORIGINATIONS SOLUTION
B10: 45226
B11: Draft Version

Sheet Product Strategy
A2: The product strategy definition can be parametrized. Currently the strategy includes 2 products and the strategy limits are part of the parameters definition
A4: Product Strategy | B4: Description | C4: Notes for ID Implementation
A5: Product Types Offered | B5: Personal Loan - Unsecured General Purpose Loan for Everyone - seperated into new-to-bank and existing customer flows Student Loan - 0% interest loan for students | C5: One decision flow covering all sub-products. Sub-products are managed with "requsted product code" field coming from Application System Product Strategy Decision Flow: 3 service calls for each flow: App.Call No = 1 => PL_Call1 App. Call No = 2 => PL_Call2 App. Call No = 3 => PL_Call3 Requested Product Codes: PL1 : Personal Loan PL2 : Student Loan
A6: Min Loan Amount | B6: 10,000 for PL1 5,000 for PL2 | C6: Constant assignment table
A7: Max Loan Amount | B7: 100,000 for PL1 50,000 for PL2 | C7: Constant assignment table
A8: Currency | B8: USD | C8: Let's assume all currencies of amounts in input and output are in USD
A9: Min Tenor | B9: 6 months for PL1 1 month for PL2 | C9: Constant assignment table
A10: Max Tenor | B10: 60 months for PL1 48 month for PL2 | C10: Constant assignment table
A11: Approval Authority (based on exposure) | B11: Loan Amount >50,000 goes to Credit Committee Loan Amount >80,000 goes to Group Retail Committee | C11: Constant assignment table
A12: Guarantor / Co-borrower Requirement | B12: Not required, as product is unsecured
A67: 62 (If pensioner loan 75)
A68: 67 (If pensioner loan 75)
A77: 6000 | B77: (It needs surety for all amounts)

Sheet Call Flows
A1: Call 1
A2: Description | B2: Personal Loans Flow Call 1: Credit Policy Knock-outs
A4: No | B4: Category | C4: Decision Flow Property | D4: Description
A5: 1 | B5: Rules / Table | C5: Initialization | D5: To set all decisions default to "Accept" and all ID outputs and calculated variables to default values For example, Income Calculation.Calculated Monthly Net Income = 0, LPA.Payment Plan Type.Accept Requested Payment Plan Type Flag = N …etc all numeric variables should be initialized to 0. Please check the data dictionary for default values of alphanumeric fields
A6: =A5+1 -> 2 | B6: Table | C6: Min Age | D6: To set minimum age requirements
A7: =A6+1 -> 3 | B7: Table | C7: Max Age | D7: To set maximum age requirements
A8: =A7+1 -> 4 | B8: Table | C8: Min Income | D8: To set minimum income requirement
A9: =A8+1 -> 5 | B9: Table | C9: Min Loan Amount | D9: To set minimum loan amount
A10: =A9+1 -> 6 | B10: Table | C10: Max Loan Amount | D10: To set maximum loan amount
A11: =A10+1 -> 7 | B11: Table | C11: Min Tenor | D11: To set minimum tenor
A12: =A11+1 -> 8 | B12: Table | C12: Max Tenor | D12: To set maximum tenor
A13: =A12+1 -> 9 | B13: Model Studio | C13: Application Scorecard | D13: To calculate the application score
A14: =A13+1 -> 10 | B14: Model Studio | C14: Behavior Scorecard | D14: To calculate the behavior score
A15: =A14+1 -> 11 | B15: Table | C15: Credit Risk Segmentation | D15: To assign the credit risk segment based on credit bureau and application / behavior score
A16: =A15+1 -> 12 | B16: Table | C16: Maximum Income Multiplier | D16: To set MIM
A17: =A16+1 -> 13 | B17: Table | C17: Maximum Unsecured Exposure | D17: To set maximum MUE
... A23: =A22+1 -> 19 | B23: Rules | C23: Final Decision | D23: To set the final decision based on triggered rules (accept, decline or refer)
A25: Call 2
A26: Description | B26: Personal Loans Flow Call 2: Minimum Eligibility Checks
A28: No | B28: Category | C28: Decision Flow Property | D28: Description
A29: 1 | B29: Rules / Table | C29: Initialization | D29: To set all decisions default to "Accept" and all ID outputs and calculated variables to default values For example, Income Calculation.Calculated Monthly Net Income = 0, LPA.Payment Plan Type.Accept Requested Payment Plan Type Flag = N …etc all numeric variables should be initialized to 0. Please check the data dictionary for default values of alphanumeric fields
A30: =A29+1 -> 2 | B30: Table | C30: Min Age | D30: To set minimum age requirements
A31: =A30+1 -> 3 | B31: Table | C31: Max Age | D31: To set maximum age requirements
A32: =A31+1 -> 4 | B32: Table | C32: Min Income | D32: To set minimum income requirement
A33: =A32+1 -> 5 | B33: Table | C33: Min Loan Amount | D33: To set minimum loan amount
A34: =A33+1 -> 6 | B34: Table | C34: Max Loan Amount | D34: To set maximum loan amount
A35: =A34+1 -> 7 | B35: Table | C35: Min Tenor | D35: To set minimum tenor
A36: =A35+1 -> 8 | B36: Table | C36: Max Tenor | D36: To set maximum tenor
A37: =A36+1 -> 9 | B37: Model Studio | C37: Application Scorecard | D37: To calculate the application score
A38: =A37+1 -> 10 | B38: Model Studio | C38: Behavior Scorecard | D38: To calculate the behavior score
A39: =A38+1 -> 11 | B39: Table | C39: Credit Risk Segmentation | D39: To assign the credit risk segment based on credit bureau and application / behavior score
A40: =A39+1 -> 12 | B40: Table | C40: Maximum Income Multiplier | D40: To set MIM
A41: =A40+1 -> 13 | B41: Table | C41: Maximum Unsecured Exposure | D41: To set maximum MUE
... A50: =A49+1 -> 22 | B50: Rules | C50: Final Decision | D50: To set the final decision based on triggered rules (accept, decline or refer)
A52: Call 3
A53: Description | B53: Personal Loans Flow Call 3: Final Credit Decision
A55: No | B55: Category | C55: Decision Flow Property | D55: Description
A56: 1 | B56: Rules / Table | C56: Initialization | D56: To set all decisions default to "Accept" and all ID outputs and calculated variables to default values For example, Income Calculation.Calculated Monthly Net Income = 0, LPA.Payment Plan Type.Accept Requested Payment Plan Type Flag = N …etc all numeric variables should be initialized to 0. Please check the data dictionary for default values of alphanumeric fields
A57: =A56+1 -> 2 | B57: Table | C57: Min Age | D57: To set minimum age requirements
A58: =A57+1 -> 3 | B58: Table | C58: Max Age | D58: To set maximum age requirements
A59: =A58+1 -> 4 | B59: Table | C59: Min Income | D59: To set minimum income requirement
A60: =A59+1 -> 5 | B60: Table | C60: Min Loan Amount | D60: To set minimum loan amount
A61: =A60+1 -> 6 | B61: Table | C61: Max Loan Amount | D61: To set maximum loan amount
A62: =A61+1 -> 7 | B62: Table | C62: Min Tenor | D62: To set minimum tenor
A63: =A62+1 -> 8 | B63: Table | C63: Max Tenor | D63: To set maximum tenor
A64: =A63+1 -> 9 | B64: Model Studio | C64: Application Scorecard | D64: To calculate the application score
A65: =A64+1 -> 10 | B65: Model Studio | C65: Behavior Scorecard | D65: To calculate the behavior score
A66: =A65+1 -> 11 | B66: Table | C66: Credit Risk Segmentation | D66: To assign the credit risk segment based on credit bureau and application / behavior score
A67: =A66+1 -> 12 | B67: Table | C67: Maximum Income Multiplier | D67: To set MIM
A68: =A67+1 -> 13 | B68: Table | C68: Maximum Unsecured Exposure | D68: To set maximum MUE
... A77: =A76+1 -> 22 | B77: Table | C77: Approval Authority | D77: To set the approver authority level

Sheet Tables
A1: These tables should be ready in the template content and be editable by the client teams at parametere level.
A2: For example, in this demo and example content, we are setting min age to 21, but client should be able to set it to 18 after purchase.
A3: Number and type of products should be able to be multiplicated as well.
A5: Table: | B5: Min Age
A6: Description: | B6: To set minimum age policy requirements
A8: Requested Product Code | B8: Min Age
A9: PL1 | B9: 20
A10: PL2 | B10: 16
A12: Table: | B12: Max Age
A13: Description: | B13: To set maximum age policy requirements
A15: Requested Product Code | B15: Max Age
A16: PL1 | B16: 65
A17: PL2 | B17: 30
A19: Table: | B19: Min Income
A20: Description: | B20: To set minimum income policy requirements
A22: Requested Product Code | B22: Min Income (monthly net)
A23: PL1 | B23: 2000
A24: PL2 | B24: 0
A26: Table: | B26: Min Loan Amount
A27: Description: | B27: To set minimum loan amount policy requirements
A29: Requested Product Code | B29: Min Loan Amount
A30: PL1 | B30: 10000
A31: PL2 | B31: 5000
A33: Table: | B33: Max Loan Amount
A34: Description: | B34: To set maximum loan amount policy requirements
A36: Requested Product Code | B36: Max Loan Amount
A37: PL1 | B37: 100000
A38: PL2 | B38: 50000
A40: Table: | B40: Min Tenor
A41: Description: | B41: To set minimum tenor policy requirements
A43: Requested Product Code | B43: Min Tenor
A44: PL1 | B44: 6
A45: PL2 | B45: 1
A47: Table: | B47: Max Tenor
A48: Description: | B48: To set maximum tenor policy requirements
A50: Requested Product Code | B50: Max Tenor
A51: PL1 | B51: 60
A52: PL2 | B52: 48
A54: Decision Table: | B54: Credit Risk Segmentation
A55: Description: | B55: Assigns the credit risk segment based on available scoring models, this could be updated according with cut off and scores chosen as well with characteristics of the credit bureau score
A57: Existing Customer Flag | B57: Behavior Score | C57: Application Probability (BAD) | D57: Credit Bureau Score | E57: Credit Risk Segment | F57: Definition
A58: Y | B58: >= 247 | E58: VL | F58: Very low risk
A59: Y | B59: 203-246 | E59: LO | F59: Low risk
A60: Y | B60: 178-202 | D60: >= 768 | E60: LO | F60: Low risk
A61: Y | B61: 178-202 | D61: 562-767 | E61: LO | F61: Low risk
A62: Y | B62: 178-202 | D62: 426-561 | E62: ME | F62: Medium risk
A63: Y | B63: 178-202 | D63: 233-425 | E63: ME | F63: Medium risk
A64: Y | B64: 178-202 | D64: <= 232 | E64: HI | F64: High Risk
A65: Y | B65: 167-177 | D65: >= 768 | E65: LO | F65: Low risk
A66: Y | B66: 167-177 | D66: 562-767 | E66: ME | F66: Medium risk
A67: Y | B67: 167-177 | D67: 426-561 | E67: ME | F67: Medium risk
A68: Y | B68: 167-177 | D68: 233-425 | E68: HI | F68: High Risk
A69: Y | B69: 167-177 | D69: <= 232 | E69: VH | F69: Very high risk
A70: Y | B70: 0-166 | D70: >= 768 | E70: ME | F70: Medium risk
A71: Y | B71: 0-166 | D71: 562-767 | E71: HI | F71: High Risk
... A74: Y | B74: 0-166 | D74: <= 232 | E74: VH | F74: Very high risk
A75: N | C75: <= 0.026 | D75: >= 768 | E75: VL | F75: Very low risk
A76: N | C76: <= 0.026 | D76: 562-767 | E76: VL | F76: Very low risk
A77: N | C77: <= 0.026 | D77: 426-561 | E77: LO | F77: Very low risk
A78: N | C78: <= 0.026 | D78: 233-425 | E78: LO | F78: Very low risk
A79: N | C79: <= 0.026 | D79: <= 232 | E79: ME | F79: Low risk
A80: N | C80: 0,026-0,027 | D80: >= 768 | E80: LO | F80: Low risk
A81: N | C81: 0,026-0,027 | D81: 562-767 | E81: LO | F81: Low risk
A82: N | C82: 0,026-0,027 | D82: 426-561 | E82: ME | F82: Low risk
A83: N | C83: 0,026-0,027 | D83: 233-425 | E83: ME | F83: Low risk
A84: N | C84: 0,026-0,027 | D84: <= 232 | E84: HI | F84: Low risk
A85: N | C85: 0,027-0,029 | D85: >= 768 | E85: LO | F85: Medium risk
A86: N | C86: 0,027-0,029 | D86: 562-767 | E86: ME | F86: Medium risk
... A94: N | C94: 0,029-0,032 | D94: <= 232 | E94: VH | F94: High Risk
A95: N | C95: >=0,032 | E95: VH | F95: Very high risk
A97: Decision Table: | B97: Maximum Income Multiplier
A98: Description: | B98: Assigns the Maximum Income Multiplier which caps the maximum eligible loan amount
A100: Requested Product Code | B100: Credit Risk Segment | C100: Income | D100: MIM
A101: PL2 | D101: 1000 | E101: Value
A102: PL1 | B102: VL, LO | C102: Low | D102: 5
A103: PL1 | B103: VL, LO | C103: Medium | D103: 10
A104: PL1 | B104: VL, LO | C104: High | D104: 12
A105: PL1 | B105: ME | C105: Low | D105: 4
A106: PL1 | B106: ME | C106: Medium | D106: 5
A107: PL1 | B107: ME | C107: High | D107: 7
A108: PL1 | B108: HI, VH | C108: Low | D108: 3
A109: PL1 | B109: HI, VH | C109: Medium | D109: 4
A110: PL1 | B110: HI, VH | C110: High | D110: 5
A112: Decision Table: | B112: Maximum Unsecured Exposure
A113: Description: | B113: Assigns the max customer exposure policy
A115: Requested Product Code | B115: Credit Risk Segment | C115: Income | D115: Maximum Unsecured Exposure
A116: PL2 | D116: 30000
A117: PL1 | B117: VL, LO | C117: Low | D117: 50000
A118: PL1 | B118: VL, LO | C118: Medium | D118: 100000
A119: PL1 | B119: VL, LO | C119: High | D119: 120000
A120: PL1 | B120: ME | C120: Low | D120: 40000
A121: PL1 | B121: ME | C121: Medium | D121: 50000
A122: PL1 | B122: ME | C122: High | D122: 70000
A123: PL1 | B123: HI, VH | C123: le | D123: 30000
A124: PL1 | B124: HI, VH | C124: Medium | D124: 40000
A125: PL1 | B125: HI, VH | C125: High | D125: 50000
A127: Decision Table: | B127: Debt burden
A128: Description: | B128: Assigns the max customer exposure requirement
A130: Requested Product Code | B130: Credit Risk Segment | C130: Income | D130: Maximum Debt Burden
A131: PL2 | D131: 50%
...

Sheet Scorecards
A1: Scorecard | B1: Application Scorecard
A2: Description: | B2: Expert Application Scorecard developed for originations decisions of Personal Loans in case required, but the methodology used was based on score models
A4: Characteristics | B4: Range | C4: Score | E4: Min Score | F4: Max Score
A5: Age | B5: < 18 Years | C5: 10 | D5: CUSTOMER_AGE | E5: =C11+C20+C27+C32+C45+C48+C54+C61+C71 -> 72 | F5: =C8+C12+C25+C28+C35+C51+C55+C65+C68 -> 254
B6: 18 - 30 Years | C6: 20
B7: 30 - 40 Years | C7: 30
B8: 40 - 50 Years | C8: 45
B9: 50+ years | C9: 40
B10: No Information | C10: 30
B11: No response | C11: 10
A12: Residential Status | B12: Belongs to Customer | C12: 35 | D12: RESIDENCE_STATUS
B13: Mortgage | C13: 30
B14: Co-Owner | C14: 25
B15: Belongs to Family | C15: 23
B16: Belongs to Someone Else | C16: 20
B17: Rent | C17: 15
B18: Other | C18: 10
B19: No Information | C19: 23
B20: No response | C20: 10
A21: Time in Current Employment (months) | B21: Less than 12 Months | C21: 10 | D21: TOTAL_EMPLOYMENT_DURATION
B22: 12 to < 24 Months | C22: 18
B23: 24 to < 48 Months | C23: 23
B24: 48 to < 60 Months | C24: 25
B25: > 60 Months | C25: 30
B26: No Information | C26: 23
B27: No response | C27: 10
A28: Marital Status | B28: Married | C28: 28 | D28: MARITAL_STATUS
B29: Widowed | C29: 20
B30: Engaged \ Co-Living | C30: 18
B31: Divorced | C31: 15
B32: Single | C32: 8
B33: No Information | C33: 18
B34: No response | C34: 8
A35: Employment Status | B35: Public Sector salaried | C35: 28 | D35: CUSTOMER_EMPLOYMENT_TYPE
B36: Private Sector salaried | C36: 25
B37: Banking / Financial Institution Salaried | C37: 25
B38: Trade | C38: 20
B39: Self-employed Professional | C39: 20
B40: Owner/Shareholder | C40: 20
B41: Farmer | C41: 15
B42: Housewife | C42: 15
B43: Student | C43: 15
B44: Retired | C44: 10
B45: Unemployed \ Immigrant | C45: 8
B46: No Information | C46: 18
B47: No response | C47: 8
A48: Education | B48: Primary | C48: 8 | D48: CUSTOMER_EDUCATION
B49: High School | C49: 10
B50: College \ University | C50: 13
B51: Masters \ Doctorate | C51: 15
B52: No Information | C52: 13
B53: No response | C53: 8
A54: Number of dependents | B54: 0 | C54: 8 | D54: CUSTOMER_DEPENDENTS_CNT
B55: 1 | C55: 18
B56: 2 | C56: 10
B57: 3 or more | C57: 10
B58: No Information | C58: 10
B59: No response | C59: 8
A60: Total Asset Size | B60: New Customer | C60: 13
B61: No Assets | C61: 5
B62: 1 - < 1000 | C62: 10
B63: 1,000 - < 10,000 | C63: 13
B64: 10,000 - <100,000 | C64: 15
B65: > 100,000 + | C65: 20
B66: No Information | C66: 13
B67: No response | C67: 5
A68: Worst Delinquency Status Last 12 Months (dpd) in credit bureau | B68: 0 | C68: 35 | D68: WPS_L12M
B69: 1-30 | C69: 28
B70: 31-60 | C70: 15
B71: 61+ | C71: 5
B72: No Match | C72: 25
B73: No Information | C73: 20
B74: No response | C74: 5
A76: Scorecard | B76: Behavior Scorecard
A77: Description: | B77: Expert Behaviou Scorecard developed for portfolio management decisions of Personal Loans
A79: Characteristics | B79: Range | C79: Score | E79: Min Score | F79: Max Score
A80: Time with Bank | B80: 1 to < 6 Months | C80: 5 | E80: =C80+C88+C92+C96+C97+C105+C109+C113+C114 -> 65 | F80: =C83+C84+C89+C93+C100+C101+C106+C110+C117 -> 380
B81: 7 to < 24 Months | C81: 20
B82: 25 to < 36 Months | C82: 40
B83: > 37 Months | C83: 50
A84: Worst delinquency in last 3 months - in-house | B84: 0 | C84: 50
B85: 1 | C85: 40
B86: 2 | C86: 30
B87: 3 | C87: 15
B88: 4+ | C88: 10
A89: % of payment cycles when cycle delinquency is greater than 0 in last 12 cycles - in-house | B89: 0-25% | C89: 40
B90: 26-50% | C90: 30
B91: 51-80% | C91: 20
B92: 81+% | C92: 10
A93: % of payment cycles when cycle delinquency is greater than 1 in last 6 cycles - in-house | B93: 0-25% | C93: 30
B94: 26-50% | C94: 15
B95: 51-80% | C95: 10
B96: 81+% | C96: 5
A97: % of cycles when payment is greater than 0 in last 12 cycles - in-house | B97: 0-25% | C97: 5
B98: 26-50% | C98: 15
B99: 51-80% | C99: 30
B100: 81+% | C100: 45
A101: Worst delinquency in last 3 months - credit bureau | B101: 0 | C101: 50
B102: 1 | C102: 40
B103: 2 | C103: 30
...

Sheet Scores
A1: Scorecard | B1: Application Scorecard
A2: Description: | B2: Application score build based on random forest
A4: BUREAU_SCORE
A5: CUSTOMER_EMPLOYMENT_TYPE
A6: DOCUMENTED_INCOME
A7: PRODUCT_CODE
A10: Scorecard | B10: Behavioral Score
A11: Description: | B11: Build with VDMML using the risk add on scorecard and interactive groupng
A14: BUREAU_CARD_UTILIZATION
A15: BUREAU_SCORE
A16: CUSTOMER_AGE
A17: CUSTOMER_EMPLOYMENT_TYPE
A18: CUSTOMER_MONTH_EXPENCES
A19: DECLARE_INCOME
A20: DOCUMENTED_INCOME
A21: WPS_AUTO_LOAN_LAST_!"M
A22: WPS_CARD_LOAN_LAST_!"M
A23: WPS_LOAN_LOAN_LAST_!"M
A24: WPS_MORTGAGE_LOAN_LAST_!"M
A25: WPS_OD_LOAN_LAST_!"M
... A29: TOTAL_NON_CARD_BALANCE
A31: Existing Customer Flag | B31: Behavior Score | C31: Application Score | D31: Credit Bureau Score | E31: Credit Risk Segment | F31: Definition
A32: Y | B32: >= 247 | E32: VL | F32: Very low risk
A33: Y | B33: 203-246 | E33: LO | F33: Low risk
A34: Y | B34: 178-202 | D34: >= 768 | E34: LO | F34: Low risk
A35: Y | B35: 178-202 | D35: 562-767 | E35: LO | F35: Low risk
A36: Y | B36: 178-202 | D36: 426-561 | E36: ME | F36: Medium risk
A37: Y | B37: 178-202 | D37: 233-425 | E37: ME | F37: Medium risk
A38: Y | B38: 178-202 | D38: <= 232 | E38: HI | F38: High Risk
A39: Y | B39: 167-177 | D39: >= 768 | E39: LO | F39: Low risk
A40: Y | B40: 167-177 | D40: 562-767 | E40: ME | F40: Medium risk
A41: Y | B41: 167-177 | D41: 426-561 | E41: ME | F41: Medium risk
A42: Y | B42: 167-177 | D42: 233-425 | E42: HI | F42: High Risk
A43: Y | B43: 167-177 | D43: <= 232 | E43: VH | F43: Very high risk
A44: Y | B44: 0-166 | D44: >= 768 | E44: ME | F44: Medium risk
A45: Y | B45: 0-166 | D45: 562-767 | E45: HI | F45: High Risk
... A48: Y | B48: 0-166 | D48: <= 232 | E48: VH | F48: Very high risk
A49: N | C49: <= 0.026 | D49: >= 768 | E49: VL | F49: Very low risk
A50: N | C50: <= 0.026 | D50: 562-767 | E50: VL | F50: Very low risk
A51: N | C51: <= 0.026 | D51: 426-561 | E51: LO | F51: Very low risk
A52: N | C52: <= 0.026 | D52: 233-425 | E52: LO | F52: Very low risk
A53: N | C53: <= 0.026 | D53: <= 232 | E53: ME | F53: Low risk
A54: N | C54: 0,026-0,027 | D54: >= 768 | E54: LO | F54: Low risk
A55: N | C55: 0,026-0,027 | D55: 562-767 | E55: LO | F55: Low risk
A56: N | C56: 0,026-0,027 | D56: 426-561 | E56: ME | F56: Low risk
A57: N | C57: 0,026-0,027 | D57: 233-425 | E57: ME | F57: Low risk
A58: N | C58: 0,026-0,027 | D58: <= 232 | E58: HI | F58: Low risk
A59: N | C59: 0,027-0,029 | D59: >= 768 | E59: LO | F59: Medium risk
A60: N | C60: 0,027-0,029 | D60: 562-767 | E60: ME | F60: Medium risk
... A68: N | C68: 0,029-0,032 | D68: <= 232 | E68: VH | F68: High Risk
A69: N | C69: >=0,032 | E69: VH | F69: Very high risk

Sheet Rules
B1: Ruleset: | C1: Initialization
B3: Rule Name | C3: Description | D3: Logic
B4: Default | C4: Initialization of decisions, output fields and calculated variables to their default figures to avoid system error | D4: To set all decisions default to "Accept" and all ID outputs and calculated variables to default values For example: Income Calculation.Calculated Monthly Net Income = 0, LPA.Payment Plan Type.Accept Requested Payment Plan Type Flag = N …etc all numeric variables should be initialized to 0. Please check the data dictionary for default values of alphanumeric fields
B5: Up-sell | C5: Determines if customer is eligible for up-sell | D5: If Risk Segmentation.Risk Segment = VL, Upsell_Flag = Y, else Upsell_Flag = N
B6: WPS_L12M | C6: Deriving "Worst CB Delinquency Status Last 12 Months (dpd)" scorecard characteristic from product level data dictionary keys | D6: WPS_L12M = Max(App.WPS Card Last 12M, App.WPS Loan Last 12M, App.WPS Mortgage Last 12M, App.WPS Auto Loan Last 12M, App.WPS OD Last 12M)
B8: Ruleset: | C8: Credit Policy Rules in call flow item: Credit Policy Rules Call 1
B10: Rule Name | C10: Description | D10: Logic | E10: Decision | F10: Reason Code
B11: Unemployed | C11: Customer is unemployed | D11: If Product code = PL1 and Employment Type = U, R, H, T | E11: Decline | F11: D101
B12: Min Income | C12: Customer's income is below policy minimum | D12: If Product code = PL1 and Declared Income < Minimum Income | E12: Decline | F12: D102
B13: Permanent Residency | C13: Customer is not a permanent resident of Country | D13: If Permanent Residence Flag = N | E13: Decline | F13: D103
B14: Pledged Account | C14: Customer has a blocked account at the bank | D14: If Pledged Amount>1000 | E14: Decline | F14: D104
B15: Min Age | C15: Customer's age is below policy minimum | D15: If Product code = PL1 and Customer's Age< 20 else if Product code = PL2 and Customer's Age < 17 | E15: Decline | F15: D105
B16: Max Age | C16: Customer is above maximum | D16: If Age > Maximum Age | E16: Decline | F16: D106
B17: Non-target_Market | C17: Customer is not in the target market of personal loans | D17: If Employment Type is in { E, O, F, M} | E17: Decline | F17: D107
B18: Job Duration | C18: Customer's job duration is less than policy minimum | D18: If Total Employment Duration < 6 and App.Employment Type = P,S,L,O,F,B | E18: Decline | F18: D108
B19: Customer has a bank legal follow up | C19: Customer has defaulted in payments and a legal follow up is initiated by the bank (in house) | D19: If App.Customer status is in L,S,W,A,R,V | E19: Decline | F19: D109
B20: Current Delinquency | C20: If customer has current delays > 30 days for any credit product at the bank (credit card, loans, overdraft etc) | D20: If Current 30 dpd number of Credit Cards>0, or Current 30 dpd number of Personal Loans>0, or Current 30 dpd number of Auto Loans>0, or Current 30 dpd number of Mortgages>0, or Current 30 dpd number of Cash Collateral>0, or Current 30 dpd number of Overdrafts>0 | E20: Decline | F20: D110
B22: Ruleset: | C22: Output Fields Call 1
B23: Rule Name | C23: Description | D23: Logic
B24: Credit Bureau Check | C24: If customer has a fresh credit bureau data, no need to do a credit bureau inquiry | D24: If Bureau Investigation Date Since>0 and Bureau Investigation Date Since<10 then call Credit Bureau with return variable CALL_BUREAU = N, else Y.
B25: Random Number | C25: To be used in champion/challenger strategy setup. RAND function should be used to create a random number between 1 to 999. | D25: Random Number = RAND()
B27: Ruleset: | C27: Credit Policy Rules in call flow item: Credit Policy Rules Call 2
B29: Rule Name | C29: Description | D29: Logic | E29: Decision | F29: Decision Reason Code
B30: Customer has a bureau legal follow up | C30: Customer has defaulted in payments and a legal follow up is initiated by the bank at credit bureau | D30: If App.WPS (Worst Payment Status) Ever = L | E30: Decline | F30: D111
B31: Very High Risk Segment | C31: According to application score x bureau score policy or behavior score x bureau score policy, score is below minimum or customer risk gement is very high | D31: If Risk Segmentation.Risk Segment = VH | E31: Decline | F31: D112
B32: No Disposable_Income | C32: Declines if there is no room in customer's current disposable income | D32: If Income Calculation.Disposable Net Income <= 0 | E32: Decline | F32: D113
B33: High Maximum_Unsecured_Exposure | C33: Declines if customer's total unsecured exposure is above policy | D33: If Limit Calculation.CustomerUnsecuredExposure> Limit Calculation.MaxCustomerUnsecuredExposure | E33: Decline | F33: D114
B34: Below Min Limit / No Room for Loan | C34: Credit limit calculated for the customer is below product minimum | D34: If Limit Calculation.App.Suggested Loan Amount<LPA.Min loan amount | E34: Decline | F34: D115
B35: High Debt Burden | C35: Debt burden calculated is higher than maximum allowed debt burden | D35: If Limit Calculation.Debt Burden Ratio > Max Debt Burden.Max Debt Burden | E35: Decline | F35: D116
B36: Credit Committee Approval | C36: Loan Amount >50,000 goes to Credit Committee | D36: If Limit Calculation.App.Suggested Loan Amount > 50000 | E36: Refer | F36: R101
B37: Group Retail Committee Approval | C37: Loan Amount >80,000 goes to Group Retail Committee | D37: If Limit Calculation.App.Suggested Loan Amount > 80000 | E37: Refer | F37: R102
B38: Customer is a staff | C38: If customer is bank's staff, HR view is required | D38: If App.Application.Staff Flag = Y | E38: Refer | F38: R104
B39: verification_needed | C39: If verification is needed for that account, OMDM sends this flag Y and PEGA parks the application for manual review | D39: If Verification Decision.Decision=Y and Verification Completed Flag=N | E39: Refer | F39: R105
B40: documentation_needed | C40: If further documentation is required, OMDM sends this flag Y and PEGA parks the application for manual review | D40: If Documentation Decision.Decision=Y and Documentation Completed Flag=N | E40: Refer | F40: R106
B41: fraud_control_main applicant | C41: Customer has an inconsistency in application information with previous applications | D41: If Home city inconsistency flag for main applicant = Y OR Business/work city inconsistency flag for main applicant = Y OR Email inconsistency flag for main applicant = Y OR Mother's maiden name inconsistency flag for main applicant = Y | E41: Refer | F41: R107 | G41: App.Bureau Fraud Flag
B44: Ruleset: | C44: Credit Policy Rules in call flow item: Credit Policy Rules Call 3 - REPEAT OF POLICY DECLINES IN CALL 1 AND 2
B46: Rule Name | C46: Description | D46: Logic | E46: Decision | F46: Decision Reason Code
B47: Unemployed | C47: Customer is unemployed | D47: If Product code = PL1 and Employment Type = U, R, H, T | E47: Decline | F47: D101
B48: Min Income | C48: Customer's income is below policy minimum | D48: If Product code = PL1 and Declared Income < Minimum Income | E48: Decline | F48: D102
B49: Permanent Residency | C49: Customer is not a permanent resident of Country | D49: If Permanent Residence Flag = N | E49: Decline | F49: D103
B50: Pledged Account | C50: Customer has a blocked account at the bank | D50: If Pledged Amount>1000 | E50: Decline | F50: D104
B51: Min Age | C51: Customer's age is below policy minimum | D51: If Product code = PL1 and Customer's Age< 20 else if Product code = PL2 and Customer's Age < 17 | E51: Decline | F51: D105
B52: Max Age | C52: Customer is above maximum | D52: If Age > Maximum Age | E52: Decline | F52: D106
B53: Non-target_Market | C53: Customer is not in the target market of personal loans | D53: If Employment Type is in { E, O, F, M} | E53: Decline | F53: D107
B54: Job Duration | C54: Customer's job duration is less than policy minimum | D54: If Total Employment Duration < 6 and App.Employment Type = P,S,L,O,F,B | E54: Decline | F54: D108
B55: Customer has a bank legal follow up | C55: Customer has defaulted in payments and a legal follow up is initiated by the bank (in house) | D55: If App.Customer status is in L,S,W,A,R,V | E55: Decline | F55: D109
B56: Current Delinquency | C56: If customer has current delays > 30 days for any credit product at the bank (credit card, loans, overdraft etc) | D56: If Current 30 dpd number of Credit Cards>0, or Current 30 dpd number of Personal Loans>0, or Current 30 dpd number of Auto Loans>0, or Current 30 dpd number of Mortgages>0, or Current 30 dpd number of Cash Collateral>0, or Current 30 dpd number of Overdrafts>0 | E56: Decline | F56: D110
B57: Customer has a bureau legal follow up | C57: Customer has defaulted in payments and a legal follow up is initiated by the bank at credit bureau | D57: If App.WPS (Worst Payment Status) Ever = L | E57: Decline | F57: D111
... B63: Customer is not eligible to requested amount | C63: Refers if customer requested amount is higher than max eligible loan amount | D63: If Requested Loan Amount > Limit Calculation.App.Suggested Loan Amount AND Limit Calculation.App.Suggested Loan Amount > 0 | E63: Refer | F63: R103
B65: Ruleset: | C65: Final Decision
B67: Rule Name | C67: Description | D67: Logic | E67: Decision | F67: Decision Reason Code
B68: call1_decision | C68: There will be several knock-out, accept or refer rules will be fired with different order and decision category. This rule will decline if any decline rule is fired, if no decline rule is fired but a refer rule is fired, will refer and if none of these then will accept to proceed to next call/action. For now only policy knock-out declines will be automated. | D68: If Call No = 1 AND C1.Policy Rules.Decision Category INCLUDES "DE" THEN Decision.Decision Category = "DE" ELSE IF C1.Policy Rules.Decision Category INCLUDES "RE" THEN Decision.Decision Category = "RE" ELSE Decision.Decision Category = "AC" | E68: Accept (AC), Decline (DE) or Refer (RE) | F68: Various
B69: call2_decision | C69: There will be several knock-out, accept or refer rules will be fired with different order and decision category. This rule will decline if any decline rule is fired, if no decline rule is fired but a refer rule is fired, will refer and if none of these then will accept to proceed to next call/action. For now, all applications will be refered to credit officer review. | D69: If Call No = 2 AND C2.Policy Rules.Decision Category INCLUDES "DE" THEN Decision.Decision Category = "DE" ELSE IF C2.Policy Rules.Decision Category INCLUDES "RE" THEN Decision.Decision Category = "RE" ELSE Decision.Decision Category = "AC" | E69: Accept (AC), Decline (DE) or Refer (RE) | F69: Various
B70: final_decision | C70: For the initial implementation, all applications will be refered to credit officer review as final decision. Hence decisions in C3.Policy Rules.Decision Category will be overriden with this simple rule. For now, all applications will be refered to credit officer review. | D70: If Call No = 3 AND C3.Policy Rules.Decision Category INCLUDES "DE" THEN Decision.Decision Category = "DE" ELSE IF C3.Policy Rules.Decision Category INCLUDES "RE" THEN Decision.Decision Category = "RE" ELSE Decision.Decision Category = "AC" | E70: Accept (AC), Decline (DE) or Refer (RE) | F70: Various
B72: Ruleset: | C72: Loan Amount Calculation
A73: Description:
A74: Logic: | B74: // Defines the customer's income based on Salary resources If Derived.SalaryIncome = Applicant.Documented Income, else if Verification Completed Flag = Y SalaryIncome = Verified Income else Income Calculation.Calculated Monthly Net Income = Declared Income New version from Zeynep - 02.03.2023 If Verification Completed Flag = Y then Income Calculation.Calculated Monthly Net Income = Verified Income else if App.Income Document flag = Y then Income Calculation.Calculated Monthly Net Income = Applicant.Documented Income, else Income Calculation.Calculated Monthly Net Income = Declared Income | G74: open personal loans
A75: Logic: | B75: // Calculates customer's monthly debt Customer Total Monthly Debt = App.Total Open Loans Installment + (0.1 % of App.Total Credit Card Balance) + App.Total Loan Installment + (0.1 % of App.Total Open Card Balance) New version from Zeynep - 02.03.2023 Derived Customer Total Monthly Debt = App.Total Loan Installment+ (0.1 % of App.Total Open Card Balance) | G75: Total credit card balance or open credit card balance
A76: Logic: | B76: // Calculates customer's disposable income Income Calculation.Disposable Net Income = Income Calculation.Calculated Monthly Net Income - Customer Total Monthly Debt - Total Monthly Expenses
A77: Logic: | B77: // Calculates customer's debt burden Limit Calculation.Debt Burden Ratio = (Customer Total Monthly Debt / Income Calculation.Calculated Monthly Net Income) * 100
A78: // Calculates customer's unsecured exposure Limit Calculation.CustomerUnsecuredExposure = App.Total Personal Loans Balance Unsecured+App.Total Credit Cards Amount+App.Total Overdrafts Amount 'Derived_MUE_Availability = Limit Calculation.MaxCustomerUnsecuredExposure - Limit Calculation.CustomerUnsecuredExposure
A79: // Calculates customer's eligibility according to MIM Derived_MIM_Availability = Derived_MIM x Income Calculation.Calculated Monthly Net Income
B80: //Calculates eligible tenor If Requested Loan Tenor > LPA.Max tenor, Limit Calculation.App.Suggested Tenor = LPA.Max tenor Else if Requested Loan Tenor < LPA.Min tenor Limit Calculation.App.Suggested Tenor = LPA.Min tenor Else Limit Calculation.App.Suggested Tenor = Requested Loan Tenor
B81: //Calculates interest rate If 'Limit Calculation.App.Suggested Tenor = 12, Derived.Interest Rate = Interest Rate for 12 months, else if Limit Calculation.App.Suggested Tenor = 24, Derived.Interest Rate = Interest Rate for 24 months, else if Limit Calculation.App.Suggested Tenor = 36, Derived.Interest Rate = Interest Rate for 36 months, else Derived.Interest Rate = Interest Rate for 48 months.
A82: // Calculates customer's eligibility according to DB // Calculate maximum installment amount using the maximum debt burden and customer's current debt burden 'Derived_DB_Availability = (Max Debt Burden.Max Debt Burden - Limit Calculation.Debt Burden Ratio) / Income Calculation.Calculated Monthly Net Income // Calculate the maximum loan amount using maximum installment amount calculated above and using suggested tenor and pricing - PV - Present Value formula is used here. 'Derived_DB_Availability = PV('Derived_DB_Availability, 'Limit Calculation.App.Suggested Tenor, Derived.Interest Rate)
B83: // Calculates suggested loan amount for the customer Limit Calculation.App.Suggested Loan Amount = MIN( 'Derived_MUE_Availability, Derived_DB_Availability, 'Derived_MIM_Availability, LPA.Max loan amount, Requested Loan Amount) If Upsell flag = Y 'Limit Calculation.App.Suggested Loan Amount = MIN( 'Derived_MUE_Availability, Derived_DB_Availability, 'Derived_MIM_Availability, LPA.Max loan amount)
B91: Ruleset: | C91: Verification Decision
A92: Description:
A93: Logic: | B93: // Determines if a verification is required If (Documented Income > 0 and Declared income > Documented Income) or If Rent > 0 Then Verification_decision flag = Y
B95: Ruleset: | C95: Documentation Decision
A96: Description:
A97: Logic: | B97: // Determines if a documentation is required If Documentation Completed Flag = N AND ( (Salary Tie-up Flag = Y and Declared income > Salary Tie-up Amount * 1.2) or If (Documentation Type = SC and Declared income > Documented income) need extra document (salary draft), if there are rent or interest income (or other) document needed THEN Documentation Decision.Decision = Y
B99: Ruleset: | C99: Deviation Decision
A100: Description:
A101: Logic: | B101: // If application is being deviated, application should not be rejected with the same reason in the next call or the processing of the same call Data Dictionary Sorted Decision Table and Sorted Reason codes array should be used to maintain this in each call for applications with Application Deviation flag = Y

Sheet Sheet1

Sheet Data Dictionary_All
A1: SAS ID UNSECURED LOAN ORIGINATIONS - DATA DICTIONARY
A2: No | B2: Data Field Name | C2: Data Field Description | D2: Used in a Rule - Name | E2: SAS ID variable name | F2: Data Category | G2: Valid Values | H2: Default Value | I2: Format | J2: Lenght | K2: Precision | L2: Array Size | M2: Mapped / Calculated | N2: Batch / Online | O2: 1.Service | P2: 2.Service | Q2: 3. Service
A3: 1 | B3: Application type | C3: In future there may be a pre-selection / pre-approval process and we may need to design a separate flow for such applications using this flag | F3: Application | G3: N:Normal, B: Batch, S: Speedy | H3: " " | I3: Alpha | J3: 1 | K3: 0 | L3: 0 | M3: M | N3: O | O3: I | P3: I | Q3: I
A4: =A3+1 -> 2 | B4: No of Sub-applications | C4: In future, there may be bundle product offers and in one application form, customer may apply for both loan and card. In this case, this variable keeps number of products requested in a single application form. | F4: Application | G4: Numeric | H4: 0 | I4: Numeric | J4: 4 | K4: 0 | L4: 0 | M4: M | N4: O | O4: I | P4: I | Q4: I
A5: =A4+1 -> 3 | B5: Channel | C5: Sales channel the application is received. | F5: Application | G5: Pls. refer to "Parameters" sheet | H5: " " | I5: Alpha | J5: 2 | K5: 0 | L5: 0 | M5: M | N5: O | O5: I | P5: I | Q5: I
A6: =A5+1 -> 4 | B6: Call No | C6: Decision engine call number | E6: CALL_ID | F6: Application | G6: 1,2,3 | H6: " " | I6: Numeric | J6: 1 | K6: 0 | L6: 0 | M6: M | N6: O | O6: I | P6: I | Q6: I
A7: =A6+1 -> 5 | B7: Country | C7: Country the application is received from | F7: Application | H7: " " | I7: Alpha | J7: 2 | K7: 0 | L7: 0 | M7: M | N7: O | O7: I | P7: I | Q7: I
A8: =A7+1 -> 6 | B8: ID Confirmation Flag | C8: Should be Y if customer's ID information is verified (KYC) | F8: Application | G8: Y/N | H8: N | I8: Alpha | J8: 1 | K8: 0 | L8: 0 | M8: M | N8: O | O8: I | P8: I | Q8: I
A9: =A8+1 -> 7 | B9: ID non-confirmation reason | C9: If ID information cannot be verified, the reason code for this | F9: Application | G9: Should be the values kept in Core System | H9: " " | I9: Alpha | J9: 2 | K9: 0 | L9: 0 | M9: M | N9: O | O9: I | P9: I | Q9: I
A10: =A9+1 -> 8 | B10: Pre-approved flag | C10: In future, for a pre-approval process, if application is from a pre-approved list, this flag should be Y | F10: Application | G10: Y/N | H10: N | I10: Alpha | J10: 1 | K10: 0 | L10: 0 | M10: M | N10: O | O10: I | P10: I | Q10: I
A11: =A10+1 -> 9 | B11: Random Number | C11: Random number generated by ID for challenger strategy development | E11: RANDOM_ID | F11: Application | G11: Numeric | H11: N/A | I11: Numeric | J11: 3 | K11: 0 | L11: 0 | M11: M | N11: O | O11: I | P11: I | Q11: I
A12: =A11+1 -> 10 | B12: Deviation flag | C12: If the application has been requested to be deviated on Core System. This flag should be on Core System screen and manually turned to Y in Core System. | F12: Application | G12: Y/N | H12: N | I12: Alpha | J12: 1 | K12: 0 | L12: 0 | M12: M | N12: O | O12: I | P12: I | Q12: I
A13: =A12+1 -> 11 | B13: Deviation Reason Codes | C13: For applications where Deviation Flag = Y, Core System should send the decline reason codes from ID's previous calls (and or same call's previous call) in an array | F13: Application | G13: ID Reason codes and explanations will be provided after strategy setup. These codes will be kept in Core System and be converted to explanations to be displayed on Core System screen. | H13: " " | I13: Alpha | J13: 4 | K13: 0 | L13: 10 | M13: M | N13: O | O13: I | P13: I | Q13: I
A14: =A13+1 -> 12 | B14: Sorted Reason Codes1 | C14: The array sent by ID in C1.Policy Rules.Sorted Reason Codes result field is sent back to ID. (If that call is processed more than once, the final status of the array should be sent) | F14: Application | G14: ID Reason codes and explanations will be provided after strategy setup. These codes will be kept in Core System and be converted to explanations to be displayed on Core System screen. | H14: " " | I14: Alpha | J14: 4 | K14: 0 | L14: 10 | M14: M | N14: O | O14: I | P14: I | Q14: I
A15: =A14+1 -> 13 | B15: Sorted Decision Table1 | C15: The array sent by ID in C1.Policy Rules.Sorted Decisions result field is sent back to ID. (If that call is processed more than once, the final status of the array should be sent) | F15: Application | H15: " " | I15: Alpha | J15: 4 | K15: 0 | L15: 10 | M15: M | N15: O | O15: I | P15: I | Q15: I
A16: =A15+1 -> 14 | B16: Sorted Reason Codes2 | C16: The array sent by ID in C2.Policy Rules.Sorted Reason Codes result field is sent back to ID. (If that call is processed more than once, the final status of the array should be sent) | F16: Application | H16: " " | I16: Alpha | J16: 4 | K16: 0 | L16: 10 | M16: M | N16: O | O16: I | P16: I | Q16: I
A17: =A16+1 -> 15 | B17: Sorted Decision Table2 | C17: The array sent by ID in C2.Policy Rules.Sorted Decisions result field is sent back to ID. (If that call is processed more than once, the final status of the array should be sent) | F17: Application | H17: " " | I17: Alpha | J17: 4 | K17: 0 | L17: 10 | M17: M | N17: O | O17: I | P17: I | Q17: I
A18: =A17+1 -> 16 | B18: Sorted Reason Codes3 | C18: The array sent by ID in C3.Policy Rules.Sorted Reason Codes result field is sent back to ID. (If that call is processed more than once, the final status of the array should be sent) | F18: Application | H18: " " | I18: Alpha | J18: 4 | K18: 0 | L18: 10 | M18: M | N18: O | O18: I | P18: I | Q18: I
A19: =A18+1 -> 17 | B19: Sorted Decision Table3 | C19: The array sent by ID in C3.Policy Rules.Sorted Decisions result field is sent back to ID. (If that call is processed more than once, the final status of the array should be sent) | F19: Application | H19: " " | I19: Alpha | J19: 4 | K19: 0 | L19: 10 | M19: M | N19: O | O19: I | P19: I | Q19: I
A20: =A19+1 -> 18 | B20: S_opinion | C20: Suspicious Opinion from Sales (KYC purposes) - Y if application is suspicious | F20: Application | G20: Y/N | H20: N | I20: Alpha | J20: 1 | K20: 0 | L20: 0 | M20: M | N20: O | O20: I | P20: I | Q20: I
A21: =A20+1 -> 19 | B21: Permanent Residence Flag | C21: Customer is a permanent resident | D21: Permanent Residence Flag | E21: PERMANENT_RESIDENT_FLG | F21: Application | G21: Y/N | H21: N | I21: Alpha | J21: 1 | K21: 0 | L21: 0 | M21: M | N21: O | O21: I | P21: I | Q21: I
A22: =A21+1 -> 20 | B22: Overtime flag | C22: If the application has received beyond working hours, this should be Y. | F22: Application | G22: Y/N | H22: N | I22: Alpha | J22: 1 | K22: 0 | L22: 0 | M22: M | N22: O | O22: I | P22: I | Q22: I
A23: =A22+1 -> 21 | B23: App.ID_Document_Flag | C23: This will be Y if ID document is completed | F23: Individual Customer | G23: Y/N | H23: N | I23: Alpha | J23: 1 | K23: 0 | L23: 0 | M23: M | N23: O | O23: I | P23: I | Q23: I
A24: =A23+1 -> 22 | B24: App.Address_Document_Flag | C24: This will be Y if Adress document is completed | F24: Individual Customer | G24: Y/N | H24: N | I24: Alpha | J24: 1 | K24: 0 | L24: 0 | M24: M | N24: O | O24: I | P24: I | Q24: I
A25: =A24+1 -> 23 | B25: App.Foreigner_Document_Flag | C25: This will be Y if Foreigner document is completed | F25: Individual Customer | G25: Y/N | H25: N | I25: Alpha | J25: 1 | K25: 0 | L25: 0 | M25: M | N25: O | O25: I | P25: I | Q25: I
A26: =A25+1 -> 24 | B26: App.Credit Bureau Completed Flag | C26: This will be Y if credit registry check is completed | F26: Individual Customer | G26: Y/N | H26: N | I26: Alpha | J26: 1 | K26: 0 | L26: 0 | M26: M | N26: O | O26: I | P26: I | Q26: I
A27: =A26+1 -> 25 | B27: Derived.Random Number | C27: Calculated by ID and sent to Core System | D27: Derived.Random Number | E27: DERIVED_RANDOM_NUMBER | F27: ID Output | G27: Numeric | H27: 0 | I27: Numeric | J27: 3 | K27: 0 | L27: 0 | M27: ID | N27: O | O27: O | P27: O | Q27: O
A28: =A27+1 -> 26 | B28: Income Calculation.Calculated Monthly Net Income | C28: Calculated by ID and sent to Core System | D28: Income Calculation.Calculated Monthly Net Income | E28: MONTHLY_NET_INCOME | F28: ID Output | G28: Numeric | H28: 0 | I28: Numeric | J28: 12 | K28: 2 | L28: 0 | M28: ID | N28: O | O28: O | P28: O | Q28: O
A29: =A28+1 -> 27 | B29: App.Income Document flag | C29: Y if income document is provided with application | E29: VERIFIED_DOCUMENT_INCOME_FLG | F29: Individual Customer | G29: Y/N | H29: N | I29: Alpha | J29: 1 | K29: 0 | L29: 0 | M29: M | N29: O | O29: I | P29: I | Q29: I
A30: =A29+1 -> 28 | B30: App.Verification Completed Flag | C30: Y if verification is completed (Zeynep 02.03.2023) | E30: VERIFICATION_COMPLETED_FLG | F30: Individual Customer | G30: Y/N | H30: N | I30: Alpha | J30: 1 | K30: 0 | L30: 0 | M30: M | N30: O | O30: I | P30: I | Q30: I
A31: =A29+1 -> 28 | B31: Income Calculation.Disposable Net Income | C31: Calculated by ID and sent to Core System | D31: Income Calculation.Disposable Net Income | E31: DISPOSABLE_NET_INCOME | F31: ID Output | G31: Numeric | H31: 0 | I31: Numeric | J31: 12 | K31: 2 | L31: 0 | M31: ID | N31: O | O31: O | P31: O | Q31: O
A32: =A31+1 -> 29 | B32: App.Documented Income fx | C32: Currency of the income on the income document | F32: Individual Customer | H32: " " | I32: Alpha | J32: 2 | K32: 0 | L32: 0 | M32: M | N32: O | O32: I | P32: I | Q32: I
A33: =A32+1 -> 30 | B33: App.Other Income | C33: Other income (if any provided) | E33: OTHER_INCOME | F33: Individual Customer | G33: Numeric | H33: 0 | I33: Numeric | J33: 10 | K33: 0 | L33: 0 | M33: M | N33: O | O33: I | P33: I | Q33: I
A34: =A33+1 -> 31 | B34: App.Other Income Fx | C34: Currency of other income (if any provided) | F34: Individual Customer | H34: " " | I34: Alpha | J34: 2 | K34: 0 | L34: 0 | M34: M | N34: O | O34: I | P34: I | Q34: I
A35: =A34+1 -> 32 | B35: App.Other Income Type | C35: Explanation / Type of the income stated as other (spouse income, rent income..etc) | F35: Individual Customer | G35: Pls. refer to "Parameters" sheet | H35: " " | I35: Alpha | J35: 1 | K35: 0 | L35: 0 | M35: M | N35: O | O35: I | P35: I | Q35: I
A36: =A35+1 -> 33 | B36: App.Other Income Duration | C36: Duration of the other income received (months) | F36: Individual Customer | G36: Numeric | H36: 0 | I36: Numeric | J36: 3 | K36: 0 | L36: 0 | M36: M | N36: O | O36: I | P36: I | Q36: I
A37: =A36+1 -> 34 | B37: Max Debt Burden.Max Debt Burden | C37: Calculated by ID and sent to Core System | D37: Max Debt Burden.Max Debt Burden | E37: MAX_DEBT_BURDEN | F37: ID Output | G37: Numeric | H37: 0 | I37: Numeric | J37: 3 | K37: 2 | L37: 0 | M37: ID | N37: O | O37: O | P37: O | Q37: O
A38: =A37+1 -> 35 | B38: App.Nationality | C38: Customer's nationality | F38: Individual Customer | G38: Pls. refer to "Parameters" sheet | H38: " " | I38: Alpha | J38: 2 | K38: 0 | L38: 0 | M38: M | N38: O | O38: I | P38: I | Q38: I
A39: =A38+1 -> 36 | B39: App.Citizenship No | C39: Cusomer's nationality number | F39: Individual Customer | G39: Numeric | H39: 0 | I39: Alpha | J39: 10 | K39: 0 | L39: 0 | M39: M | N39: O | O39: I | P39: I | Q39: I
A40: =A39+1 -> 37 | B40: App.Tax Number | C40: Cusomer's tax number | F40: Individual Customer | G40: Numeric | H40: 0 | I40: Alpha | J40: 10 | K40: 0 | L40: 0 | M40: M | N40: O | O40: I | P40: I | Q40: I
A41: =A40+1 -> 38 | B41: App.Business Adress City | C41: City of the customer's employer's address | F41: Individual Customer | G41: Pls. refer to "Parameters" sheet | H41: " " | I41: Alpha | J41: 3 | K41: 0 | L41: 0 | M41: M | N41: O | O41: I | P41: I | Q41: I
A42: =A41+1 -> 39 | B42: App.Business Adress Country | C42: Country of the customer's employer's address | F42: Individual Customer | G42: Pls. refer to "Parameters" sheet | H42: " " | I42: Alpha | J42: 2 | K42: 0 | L42: 0 | M42: M | N42: O | O42: I | P42: I | Q42: I
A43: =A42+1 -> 40 | B43: App.Education | C43: Customer's education level | E43: CUSTOMER_EDUCATION | F43: Individual Customer | G43: Pls. refer to "Parameters" sheet | H43: " " | I43: Alpha | J43: 1 | K43: 0 | L43: 0 | M43: M | N43: O | O43: I | P43: I | Q43: I
A44: =A43+1 -> 41 | B44: Limit Calculation.App.Suggested Loan Amount | C44: Calculated by ID and sent to Core System | D44: Limit Calculation.App.Suggested Loan Amount | E44: SUGGESTED_LOAN_AMOUNT | F44: ID Output | G44: Numeric | H44: 0 | I44: Numeric | J44: 12 | K44: 0 | L44: 0 | M44: ID | N44: O | O44: O | P44: O | Q44: O
A45: =A44+1 -> 42 | B45: App.Latest Residence Duration | C45: Duration the customer lived in latest house (in months) | F45: Individual Customer | G45: Numeric | H45: 0 | I45: Numeric | J45: 4 | K45: 0 | L45: 0 | M45: M | N45: O | O45: I | P45: I | Q45: I
A46: =A45+1 -> 43 | B46: App.Latest Business Duration | C46: Duration the customer worked for latest employer (in months) | F46: Individual Customer | G46: Numeric | H46: 0 | I46: Numeric | J46: 4 | K46: 0 | L46: 0 | M46: M | N46: O | O46: I | P46: I | Q46: I
A47: =A46+1 -> 44 | B47: Limit Calculation.Debt Burden Ratio | C47: Debt burden ratio calculated by ID | D47: Limit Calculation.Debt Burden Ratio | E47: DEBT_BURDEN_RATIO | F47: ID Output | G47: Numeric | H47: 0 | I47: Numeric | J47: 3 | K47: 2 | L47: 0 | M47: ID | N47: O | O47: O | P47: O | Q47: O
A48: =A47+1 -> 45 | B48: App.Gender | C48: Customer's gender | F48: Individual Customer | G48: Pls. refer to "Parameters" sheet | H48: " " | I48: Alpha | J48: 1 | K48: 0 | L48: 0 | M48: M | N48: O | O48: I | P48: I | Q48: I
A49: =A48+1 -> 46 | B49: App.Home Adress City | C49: City of the customer's home address | F49: Individual Customer | G49: Pls. refer to "Parameters" sheet | H49: " " | I49: Alpha | J49: 3 | K49: 0 | L49: 0 | M49: M | N49: O | O49: I | P49: I | Q49: I
A50: =A49+1 -> 47 | B50: App.Home Adress Country | C50: Country of the customer's home address | F50: Individual Customer | G50: Pls. refer to "Parameters" sheet | H50: " " | I50: Alpha | J50: 2 | K50: 0 | L50: 0 | M50: M | N50: O | O50: I | P50: I | Q50: I
A51: =A50+1 -> 48 | B51: App.VIP Flag | C51: Y if customer is VIP | F51: Individual Customer | G51: Y/N | H51: N | I51: Alpha | J51: 1 | K51: 0 | L51: 0 | M51: M | N51: O | O51: I | P51: I | Q51: I
A52: =A51+1 -> 49 | B52: App.KEY Person | C52: Y if customer is KEY for some relation with Bank (someone having business relation with the bank) | F52: Individual Customer | G52: Y/N | H52: N | I52: Alpha | J52: 1 | K52: 0 | L52: 0 | M52: M | N52: O | O52: I | P52: I | Q52: I
A53: =A52+1 -> 50 | B53: App.Marrital Status | C53: Marrital status of the customer | E53: MARITAL_STATUS | F53: Individual Customer | G53: Pls. refer to "Parameters" sheet | H53: " " | I53: Alpha | J53: 1 | K53: 0 | L53: 0 | M53: M | N53: O | O53: I | P53: I | Q53: I
A54: =A53+1 -> 51 | B54: App.Mobile Phone Number | C54: Mobile Phone Number | F54: Individual Customer | G54: Numeric | H54: 0 | I54: Numeric | J54: 12 | K54: 0 | L54: 0 | M54: M | N54: O | O54: I | P54: I | Q54: I
A55: =A54+1 -> 52 | B55: App.Business Phone Area Code | C55: Business Phone Area Code | F55: Individual Customer | G55: Numeric | H55: 0 | I55: Numeric | J55: 4 | K55: 0 | L55: 0 | M55: M | N55: O | O55: I | P55: I | Q55: I
A56: =A55+1 -> 53 | B56: App.Home Tel Area Code | C56: Home tel area code | F56: Individual Customer | G56: Numeric | H56: 0 | I56: Numeric | J56: 4 | K56: 0 | L56: 0 | M56: M | N56: O | O56: I | P56: I | Q56: I
A57: =A56+1 -> 54 | B57: App.Occupation Code | C57: Occupation | F57: Individual Customer | G57: Pls. refer to "Parameters" sheet | H57: " " | I57: Alpha | J57: 2 | K57: 0 | L57: 0 | M57: C | N57: O | O57: I | P57: I | Q57: I
A58: =A57+1 -> 55 | B58: App.Residence Type | C58: Ownership of the house | E58: RESIDENCE_STATUS | F58: Individual Customer | G58: Pls. refer to "Parameters" sheet | H58: " " | I58: Alpha | J58: 1 | K58: 0 | L58: 0 | M58: M | N58: O | O58: I | P58: I | Q58: I
A59: =A58+1 -> 56 | B59: App.Address Unique Number | C59: Address Unique Number | F59: Individual Customer | H59: " " | I59: Alpha | J59: 16 | K59: 0 | L59: 0 | M59: M | N59: O | O59: I | P59: I | Q59: I
A60: =A59+1 -> 57 | B60: App.Rent | C60: Rent amount (if customer states s/he has rental income) | E60: RENT_INCOME | F60: Individual Customer | G60: Numeric | H60: 0 | I60: Numeric | J60: 10 | K60: 0 | L60: 0 | M60: M | N60: O | O60: I | P60: I | Q60: I
A61: =A60+1 -> 58 | B61: App.Business Residence Type | C61: Ownership of the work place (for sel-emploed, professionals, micro in future) | F61: Individual Customer | G61: Pls. refer to "Parameters" sheet | H61: " " | I61: Alpha | J61: 1 | K61: 0 | L61: 0 | M61: M | N61: O | O61: I | P61: I | Q61: I
A62: =A61+1 -> 59 | B62: Limit Calculation.CustomerUnsecuredExposure | C62: Customer MUE in bank calculated in ID | D62: Limit Calculation.CustomerUnsecuredExposure | E62: UNSECURED_EXPOSURE | F62: ID Output | G62: Numeric | H62: 0 | I62: Numeric | J62: 12 | K62: 0 | L62: 0 | M62: ID | N62: O | O62: O | P62: O | Q62: O
A63: =A62+1 -> 60 | B63: App.No of Owned Cars | C63: Number of cars owned by the customer | F63: Individual Customer | G63: Numeric | H63: 0 | I63: Numeric | J63: 3 | K63: 0 | L63: 0 | M63: M | N63: O | O63: I | P63: I | Q63: I
A64: =A63+1 -> 61 | B64: App.Total Deposit in Bank | C64: Total amount in Deposit accounts of the customer in Bank | F64: Individual Customer | G64: Numeric | H64: 0 | I64: Numeric | J64: 12 | K64: 0 | L64: 0 | M64: M | N64: O | O64: I | P64: I | Q64: I
A65: =A64+1 -> 62 | B65: App.Avg Deposit Balance last6m | C65: Average balance amount for the last 6 months | F65: Individual Customer | G65: Numeric | H65: 0 | I65: Numeric | J65: 12 | K65: 0 | L65: 0 | M65: M | N65: O | O65: I | P65: I | Q65: I
A66: =A65+1 -> 63 | B66: App.Avg Balance Statement last6m | C66: Average statement amount for the last 6 months | F66: Individual Customer | G66: Numeric | H66: 0 | I66: Numeric | J66: 12 | K66: 0 | L66: 0 | M66: M | N66: O | O66: I | P66: I | Q66: I
A67: =A66+1 -> 64 | B67: App.Current Account Duration | C67: Total duration customer has a current account with bank (months) | F67: Individual Customer | G67: Numeric | H67: 0 | I67: Numeric | J67: 4 | K67: 0 | L67: 0 | M67: M | N67: O | O67: I | P67: I | Q67: I
A68: =A67+1 -> 65 | B68: App.Total Savings in Bank | C68: Total amount in Saving accounts of the customer in Bank | F68: Individual Customer | G68: Numeric | H68: 0 | I68: Numeric | J68: 12 | K68: 0 | L68: 0 | M68: M | N68: O | O68: I | P68: I | Q68: I
A69: =A68+1 -> 66 | B69: App.Time till Deposit Maturity | C69: Total time (in months) until term deposit account maturity for the customer (the account with more number of months to maturity if there is more than one such account of the customer) | F69: Individual Customer | G69: Numeric | H69: 0 | I69: Numeric | J69: 4 | K69: 0 | L69: 0 | M69: M | N69: O | O69: I | P69: I | Q69: I
A70: =A69+1 -> 67 | B70: App.Work Position | C70: Work Position of the Customer | F70: Individual Customer | G70: Pls. refer to "Parameters" sheet | H70: " " | I70: Alpha | J70: 2 | K70: 0 | L70: 0 | M70: M | N70: O | O70: I | P70: I | Q70: I
A71: =A70+1 -> 68 | B71: App.No of dependents | C71: No of dependents | E71: CUSTOMER_DEPENDENTS_CNT | F71: Individual Customer | G71: Numeric | H71: 0 | I71: Numeric | J71: 3 | K71: 0 | L71: 0 | M71: M | N71: O | O71: I | P71: I | Q71: I
A72: =A71+1 -> 69 | B72: App.Salary Tie-up Flag | C72: Flag to show if customer is already a salary tie-up customer of the bank | E72: SALARY_TIE_UP_FLG | F72: Individual Customer | G72: Y/N | H72: N | I72: Alpha | J72: 1 | K72: 0 | L72: 0 | M72: M | N72: O | O72: I | P72: I | Q72: I
A73: =A72+1 -> 70 | B73: App.Salary Tie-up Amount | C73: Salary of the Bank's salary tie-up customer | E73: SALARY_TIE_UP_AMOUNT | F73: Individual Customer | G73: Numeric | H73: 0 | I73: Numeric | J73: 10 | K73: 0 | L73: 0 | M73: M | N73: O | O73: I | P73: I | Q73: I
A74: =A73+1 -> 71 | B74: Limit Calculation.MaxCustomerUnsecuredExposure | C74: Max Customer MUE allowed by policy | D74: Limit Calculation.MaxCustomerUnsecuredExposure | E74: MAX_UNSECURED_EXPOSURE | F74: ID Output | G74: Numeric | H74: 0 | I74: Numeric | J74: 12 | K74: 0 | L74: 0 | M74: ID | N74: O | O74: O | P74: O | Q74: O
A75: =A74+1 -> 72 | B75: C1.Policy Rules.Decision Category | C75: Calculated by ID and sent to Core System | D75: C1.Policy Rules.Decision Category | E75: C1_DECISION_CATEGORY | F75: ID Output | H75: " " | I75: Alpha | J75: 20 | K75: 0 | L75: 0 | M75: ID | N75: O | O75: O
A76: =A75+1 -> 73 | B76: App.Predefined Company Flag | C76: Flag to show if customer is employed in a predefined company | F76: Individual Customer | G76: Y/N | H76: N | I76: Alpha | J76: 1 | K76: 0 | L76: 0 | M76: M | N76: O | O76: I | P76: I | Q76: I
A77: =A76+1 -> 74 | B77: Risk Segmentation.Risk Segment | C77: Calculated by ID and sent to Core System | D77: Risk Segmentation.Risk Segment | E77: RISK_SEGMENT | F77: ID Output | H77: " " | I77: Alpha | J77: 2 | K77: 0 | L77: 0 | M77: ID | N77: O | P77: O | Q77: O
A78: =A77+1 -> 75 | B78: C2.Policy Rules.Decision Category | C78: Calculated by ID and sent to Core System | D78: C2.Policy Rules.Decision Category | E78: C2_DECISION_CATEGORY | F78: ID Output | H78: " " | I78: Alpha | J78: 20 | K78: 0 | L78: 0 | M78: ID | N78: O | P78: O
A79: =A78+1 -> 76 | B79: Requested Loan Amount Fx | C79: Currency of Requested Loan Amount | F79: Requested Product | H79: " " | I79: Alpha | J79: 2 | K79: 0 | L79: 0 | M79: M | N79: O | O79: I | P79: I | Q79: I
A80: =A79+1 -> 77 | B80: Requested Loan Tenor | C80: Requested Loan Tenor | E80: REQUESTED_LOAN_TENOR | F80: Requested Product | G80: Numeric | H80: 0 | I80: Numeric | J80: 3 | K80: 0 | L80: 0 | M80: M | N80: O | O80: I | P80: I | Q80: I
A81: =A80+1 -> 78 | B81: Requested Loan EMI | C81: Requested Loan EMI (equal monthly installment) - if asked? | F81: Requested Product | G81: Numeric | H81: 0 | I81: Numeric | J81: 10 | K81: 0 | L81: 0 | M81: M | N81: O | O81: I | P81: I | Q81: I
A82: =A81+1 -> 79 | B82: C3.LPA.Min loan amount | C82: Calculated by ID and sent to Core System | D82: C3.LPA.Min loan amount | E82: C3_MIN_LOAN_AMOUNT | F82: ID Output | G82: Numeric | H82: 0 | I82: Numeric | J82: 12 | K82: 2 | L82: 0 | M82: ID | N82: O | Q82: O
A83: =A82+1 -> 80 | B83: Interest Rate for 12 months | C83: Shall we retrieve this as we can offer different tenor based on eligible amount? | E83: INTEREST_RATE_12 | F83: Requested Product | G83: Numeric | H83: 0 | I83: Numeric | J83: 4 | K83: 2 | L83: 0 | M83: M | N83: O | O83: I | P83: I | Q83: I
A84: =A83+1 -> 81 | B84: Interest Rate for 18 months | C84: Shall we retrieve this as we can offer different tenor based on eligible amount? | E84: INTEREST_RATE_18 | F84: Requested Product | G84: Numeric | H84: 0 | I84: Numeric | J84: 4 | K84: 2 | L84: 0 | M84: M | N84: O | O84: I | P84: I | Q84: I
A85: =A84+1 -> 82 | B85: Interest Rate for 24 months | C85: Shall we retrieve this as we can offer different tenor based on eligible amount? | E85: INTEREST_RATE_24 | F85: Requested Product | G85: Numeric | H85: 0 | I85: Numeric | J85: 4 | K85: 2 | L85: 0 | M85: M | N85: O | O85: I | P85: I | Q85: I
A86: =A85+1 -> 83 | B86: Interest Rate for 36 months | C86: Shall we retrieve this as we can offer different tenor based on eligible amount? | E86: INTEREST_RATE_36 | F86: Requested Product | G86: Numeric | H86: 0 | I86: Numeric | J86: 4 | K86: 2 | L86: 0 | M86: M | N86: O | O86: I | P86: I | Q86: I
A87: =A86+1 -> 84 | B87: Interest Rate for 48 months | C87: Shall we retrieve this as we can offer different tenor based on eligible amount? | E87: INTEREST_RATE_48 | F87: Requested Product | G87: Numeric | H87: 0 | I87: Numeric | J87: 4 | K87: 2 | L87: 0 | M87: M | N87: O | O87: I | P87: I | Q87: I
A88: =A87+1 -> 85 | B88: Interest Rate for 60 months | C88: Shall we retrieve this as we can offer different tenor based on eligible amount? | E88: INTEREST_RATE_60 | F88: Requested Product | G88: Numeric | H88: 0 | I88: Numeric | J88: 4 | K88: 2 | L88: 0 | M88: M | N88: O | O88: I | P88: I | Q88: I
A89: =A88+1 -> 86 | B89: C3.Policy Rules.Decision Category | C89: Calculated by ID and sent to Core System | D89: C3.Policy Rules.Decision Category | E89: C3_DECISION_CATEGORY | F89: ID Output | H89: " " | I89: Alpha | J89: 20 | K89: 0 | L89: 0 | M89: ID | N89: O | Q89: O
A90: =A89+1 -> 87 | B90: Loan purpose | C90: Loan Purpose (Parameter table) | F90: Requested Product | G90: Pls. refer to "Parameters" sheet | H90: " " | I90: Alpha | J90: 2 | K90: 0 | L90: 0 | M90: M | N90: O | O90: I | P90: I | Q90: I
A91: =A90+1 -> 88 | B91: App.Bureau Response Number | C91: Unique number provided by Bureau for inquiry | F91: Individual Bureau | H91: " " | I91: Alpha | J91: 20 | K91: 0 | L91: 0 | M91: C | N91: O | P91: I | Q91: I
A92: =A91+1 -> 89 | B92: Upsell Flag | C92: Customer is eligible for upsel or not | D92: Upsell_Flag | E92: UPSELL_FLG | F92: ID Output | G92: Y/N | H92: " " | I92: Alpha | J92: 1 | K92: 0 | L92: 0 | M92: ID | N92: O | Q92: O
A93: =A92+1 -> 90 | B93: App.Bureau Customer Indebtness Index | C93: For future use | F93: Individual Bureau | H93: " " | I93: Alpha | J93: 3 | K93: 0 | L93: 0 | M93: M | N93: O | P93: I | Q93: I
A94: =A93+1 -> 91 | B94: App.Bureau ID | C94: For future use | F94: Individual Bureau | H94: " " | I94: Alpha | J94: 1 | K94: 0 | L94: 0 | M94: C | N94: O | P94: I | Q94: I
A95: =A94+1 -> 92 | B95: App.Bureau Score | C95: For future use | E95: BUREAU_SCORE | F95: Individual Bureau | G95: Numeric | H95: 0 | I95: Numeric | J95: 4 | K95: 0 | L95: 0 | M95: C | N95: O | P95: I | Q95: I
A96: =A95+1 -> 93 | B96: App.Bureau Score Reason | C96: For future use | F96: Individual Bureau | H96: " " | I96: Alpha | J96: 8 | K96: 0 | L96: 0 | M96: C | N96: O | P96: I | Q96: I
A97: =A96+1 -> 94 | B97: App.Bureau Not Scored Reason | C97: For future use | F97: Individual Bureau | H97: " " | I97: Alpha | J97: 1 | K97: 0 | L97: 0 | M97: M | N97: O | P97: I | Q97: I
A98: =A97+1 -> 95 | B98: App.Bureau Score Version | C98: For future use | F98: Individual Bureau | H98: " " | I98: Alpha | J98: 1 | K98: 0 | L98: 0 | M98: M | N98: O | P98: I | Q98: I
A99: =A98+1 -> 96 | B99: App.Total Non-Card Balance | C99: For future use | E99: TOTAL_NON_CARD_BALANCE | F99: Individual Bureau | G99: Numeric | H99: 0 | I99: Numeric | J99: 12 | K99: 0 | L99: 0 | M99: C | N99: O | P99: I | Q99: I
A100: =A99+1 -> 97 | B100: App.Max Duration Since Opening of an Open Card | C100: For future use | E100: MAX_DUR_SINCE_CC_OPEN | F100: Individual Bureau | G100: Numeric | H100: 0 | I100: Numeric | J100: 4 | K100: 0 | L100: 0 | M100: C | N100: O | P100: I | Q100: I
...

Sheet Data Dictionary Used
A1: SAS ID UNSECURED LOAN ORIGINATIONS - DATA DICTIONARY
A2: No | B2: Data Field Name | C2: Data Field Description | D2: Used in a Rule - Name | E2: SAS ID variable name | F2: Data Category | G2: Valid Values | H2: Default Value | I2: Format | J2: Lenght | K2: Precision | L2: Array Size | M2: Mapped / Calculated | N2: Batch / Online | O2: 1.Service | P2: 2.Service | Q2: 3. Service
A3: 1 | B3: Application type | C3: In future there may be a pre-selection / pre-approval process and we may need to design a separate flow for such applications using this flag | F3: Application | G3: N:Normal, B: Batch, S: Speedy | H3: " " | I3: Alpha | J3: 1 | K3: 0 | L3: 0 | M3: M | N3: O | O3: I | P3: I | Q3: I
A4: =+A3+1 -> 2 | B4: Call No | C4: Decision engine call number | E4: CALL_ID | F4: Application | G4: 1,2,3 | H4: " " | I4: Numeric | J4: 1 | K4: 0 | L4: 0 | M4: M | N4: O | O4: I | P4: I | Q4: I
A5: =+A4+1 -> 3 | B5: Random Number | C5: Random number generated by ID for challenger strategy development | E5: RANDOM_ID | F5: Application | G5: Numeric | H5: N/A | I5: Numeric | J5: 3 | K5: 0 | L5: 0 | M5: M | N5: O | O5: I | P5: I | Q5: I
A6: =+A5+1 -> 4 | B6: Permanent Residence Flag | C6: Customer is a permanent resident | D6: Permanent Residence Flag | E6: PERMANENT_RESIDENT_FLG | F6: Application | G6: Y/N | H6: N | I6: Alpha | J6: 1 | K6: 0 | L6: 0 | M6: M | N6: O | O6: I | P6: I | Q6: I
A7: =+A6+1 -> 5 | B7: Derived.Random Number | C7: Calculated by ID and sent to Core System | D7: Derived.Random Number | E7: DERIVED_RANDOM_NUMBER | F7: ID Output | G7: Numeric | H7: 0 | I7: Numeric | J7: 3 | K7: 0 | L7: 0 | M7: ID | N7: O | O7: O | P7: O | Q7: O
A8: =+A7+1 -> 6 | B8: Income Calculation.Calculated Monthly Net Income | C8: Calculated by ID and sent to Core System | D8: Income Calculation.Calculated Monthly Net Income | E8: MONTHLY_NET_INCOME | F8: ID Output | G8: Numeric | H8: 0 | I8: Numeric | J8: 12 | K8: 2 | L8: 0 | M8: ID | N8: O | O8: O | P8: O | Q8: O
A9: =+A8+1 -> 7 | B9: App.Income Document flag | C9: Y if income document is provided with application | E9: VERIFIED_DOCUMENT_INCOME_FLG | F9: Individual Customer | G9: Y/N | H9: N | I9: Alpha | J9: 1 | K9: 0 | L9: 0 | M9: M | N9: O | O9: I | P9: I | Q9: I
A10: =+A9+1 -> 8 | B10: App.Verification Completed Flag | C10: Y if verification is completed (Zeynep 02.03.2023) | E10: VERIFICATION_COMPLETED_FLG | F10: Individual Customer | G10: Y/N | H10: N | I10: Alpha | J10: 1 | K10: 0 | L10: 0 | M10: M | N10: O | O10: I | P10: I | Q10: I
A11: =+A10+1 -> 9 | B11: Income Calculation.Disposable Net Income | C11: Calculated by ID and sent to Core System | D11: Income Calculation.Disposable Net Income | E11: DISPOSABLE_NET_INCOME | F11: ID Output | G11: Numeric | H11: 0 | I11: Numeric | J11: 12 | K11: 2 | L11: 0 | M11: ID | N11: O | O11: O | P11: O | Q11: O
A12: =+A11+1 -> 10 | B12: App.Other Income | C12: Other income (if any provided) | E12: OTHER_INCOME | F12: Individual Customer | G12: Numeric | H12: 0 | I12: Numeric | J12: 10 | K12: 0 | L12: 0 | M12: M | N12: O | O12: I | P12: I | Q12: I
A13: =+A12+1 -> 11 | B13: Max Debt Burden.Max Debt Burden | C13: Calculated by ID and sent to Core System | D13: Max Debt Burden.Max Debt Burden | E13: MAX_DEBT_BURDEN | F13: ID Output | G13: Numeric | H13: 0 | I13: Numeric | J13: 3 | K13: 2 | L13: 0 | M13: ID | N13: O | O13: O | P13: O | Q13: O
A14: =+A13+1 -> 12 | B14: App.Education | C14: Customer's education level | E14: CUSTOMER_EDUCATION | F14: Individual Customer | G14: Pls. refer to "Parameters" sheet | H14: " " | I14: Alpha | J14: 1 | K14: 0 | L14: 0 | M14: M | N14: O | O14: I | P14: I | Q14: I
A15: =+A14+1 -> 13 | B15: Limit Calculation.App.Suggested Loan Amount | C15: Calculated by ID and sent to Core System | D15: Limit Calculation.App.Suggested Loan Amount | E15: SUGGESTED_LOAN_AMOUNT | F15: ID Output | G15: Numeric | H15: 0 | I15: Numeric | J15: 12 | K15: 0 | L15: 0 | M15: ID | N15: O | O15: O | P15: O | Q15: O
A16: =+A15+1 -> 14 | B16: Limit Calculation.Debt Burden Ratio | C16: Debt burden ratio calculated by ID | D16: Limit Calculation.Debt Burden Ratio | E16: DEBT_BURDEN_RATIO | F16: ID Output | G16: Numeric | H16: 0 | I16: Numeric | J16: 3 | K16: 2 | L16: 0 | M16: ID | N16: O | O16: O | P16: O | Q16: O
A17: =+A16+1 -> 15 | B17: App.Marrital Status | C17: Marrital status of the customer | E17: MARITAL_STATUS | F17: Individual Customer | G17: Pls. refer to "Parameters" sheet | H17: " " | I17: Alpha | J17: 1 | K17: 0 | L17: 0 | M17: M | N17: O | O17: I | P17: I | Q17: I
A18: =+A17+1 -> 16 | B18: App.Residence Type | C18: Ownership of the house | E18: RESIDENCE_STATUS | F18: Individual Customer | G18: Pls. refer to "Parameters" sheet | H18: " " | I18: Alpha | J18: 1 | K18: 0 | L18: 0 | M18: M | N18: O | O18: I | P18: I | Q18: I
A19: =+A18+1 -> 17 | B19: App.Rent | C19: Rent amount (if customer states s/he has rental income) | E19: RENT_INCOME | F19: Individual Customer | G19: Numeric | H19: 0 | I19: Numeric | J19: 10 | K19: 0 | L19: 0 | M19: M | N19: O | O19: I | P19: I | Q19: I
A20: =+A19+1 -> 18 | B20: Limit Calculation.CustomerUnsecuredExposure | C20: Customer MUE in bank calculated in ID | D20: Limit Calculation.CustomerUnsecuredExposure | E20: UNSECURED_EXPOSURE | F20: ID Output | G20: Numeric | H20: 0 | I20: Numeric | J20: 12 | K20: 0 | L20: 0 | M20: ID | N20: O | O20: O | P20: O | Q20: O
A21: =+A20+1 -> 19 | B21: App.No of dependents | C21: No of dependents | E21: CUSTOMER_DEPENDENTS_CNT | F21: Individual Customer | G21: Numeric | H21: 0 | I21: Numeric | J21: 3 | K21: 0 | L21: 0 | M21: M | N21: O | O21: I | P21: I | Q21: I
A22: =+A21+1 -> 20 | B22: App.Salary Tie-up Flag | C22: Flag to show if customer is already a salary tie-up customer of the bank | E22: SALARY_TIE_UP_FLG | F22: Individual Customer | G22: Y/N | H22: N | I22: Alpha | J22: 1 | K22: 0 | L22: 0 | M22: M | N22: O | O22: I | P22: I | Q22: I
A23: =+A22+1 -> 21 | B23: App.Salary Tie-up Amount | C23: Salary of the Bank's salary tie-up customer | E23: SALARY_TIE_UP_AMOUNT | F23: Individual Customer | G23: Numeric | H23: 0 | I23: Numeric | J23: 10 | K23: 0 | L23: 0 | M23: M | N23: O | O23: I | P23: I | Q23: I
A24: =+A23+1 -> 22 | B24: Limit Calculation.MaxCustomerUnsecuredExposure | C24: Max Customer MUE allowed by policy | D24: Limit Calculation.MaxCustomerUnsecuredExposure | E24: MAX_UNSECURED_EXPOSURE | F24: ID Output | G24: Numeric | H24: 0 | I24: Numeric | J24: 12 | K24: 0 | L24: 0 | M24: ID | N24: O | O24: O | P24: O | Q24: O
A25: =+A24+1 -> 23 | B25: C1.Policy Rules.Decision Category | C25: Calculated by ID and sent to Core System | D25: C1.Policy Rules.Decision Category | E25: C1_DECISION_CATEGORY | F25: ID Output | H25: " " | I25: Alpha | J25: 20 | K25: 0 | L25: 0 | M25: ID | N25: O | O25: O
A26: =+A25+1 -> 24 | B26: Risk Segmentation.Risk Segment | C26: Calculated by ID and sent to Core System | D26: Risk Segmentation.Risk Segment | E26: RISK_SEGMENT | F26: ID Output | H26: " " | I26: Alpha | J26: 2 | K26: 0 | L26: 0 | M26: ID | N26: O | P26: O | Q26: O
A27: =+A26+1 -> 25 | B27: C2.Policy Rules.Decision Category | C27: Calculated by ID and sent to Core System | D27: C2.Policy Rules.Decision Category | E27: C2_DECISION_CATEGORY | F27: ID Output | H27: " " | I27: Alpha | J27: 20 | K27: 0 | L27: 0 | M27: ID | N27: O | P27: O
A28: =+A27+1 -> 26 | B28: Requested Loan Tenor | C28: Requested Loan Tenor | E28: REQUESTED_LOAN_TENOR | F28: Requested Product | G28: Numeric | H28: 0 | I28: Numeric | J28: 3 | K28: 0 | L28: 0 | M28: M | N28: O | O28: I | P28: I | Q28: I
A29: =+A28+1 -> 27 | B29: C3.LPA.Min loan amount | C29: Calculated by ID and sent to Core System | D29: C3.LPA.Min loan amount | E29: C3_MIN_LOAN_AMOUNT | F29: ID Output | G29: Numeric | H29: 0 | I29: Numeric | J29: 12 | K29: 2 | L29: 0 | M29: ID | N29: O | Q29: O
A30: =+A29+1 -> 28 | B30: Interest Rate for 12 months | C30: Shall we retrieve this as we can offer different tenor based on eligible amount? | E30: INTEREST_RATE_12 | F30: Requested Product | G30: Numeric | H30: 0 | I30: Numeric | J30: 4 | K30: 2 | L30: 0 | M30: M | N30: O | O30: I | P30: I | Q30: I
A31: =+A30+1 -> 29 | B31: Interest Rate for 18 months | C31: Shall we retrieve this as we can offer different tenor based on eligible amount? | E31: INTEREST_RATE_18 | F31: Requested Product | G31: Numeric | H31: 0 | I31: Numeric | J31: 4 | K31: 2 | L31: 0 | M31: M | N31: O | O31: I | P31: I | Q31: I
A32: =+A31+1 -> 30 | B32: Interest Rate for 24 months | C32: Shall we retrieve this as we can offer different tenor based on eligible amount? | E32: INTEREST_RATE_24 | F32: Requested Product | G32: Numeric | H32: 0 | I32: Numeric | J32: 4 | K32: 2 | L32: 0 | M32: M | N32: O | O32: I | P32: I | Q32: I
A33: =+A32+1 -> 31 | B33: Interest Rate for 36 months | C33: Shall we retrieve this as we can offer different tenor based on eligible amount? | E33: INTEREST_RATE_36 | F33: Requested Product | G33: Numeric | H33: 0 | I33: Numeric | J33: 4 | K33: 2 | L33: 0 | M33: M | N33: O | O33: I | P33: I | Q33: I
A34: =+A33+1 -> 32 | B34: Interest Rate for 48 months | C34: Shall we retrieve this as we can offer different tenor based on eligible amount? | E34: INTEREST_RATE_48 | F34: Requested Product | G34: Numeric | H34: 0 | I34: Numeric | J34: 4 | K34: 2 | L34: 0 | M34: M | N34: O | O34: I | P34: I | Q34: I
A35: =+A34+1 -> 33 | B35: Interest Rate for 60 months | C35: Shall we retrieve this as we can offer different tenor based on eligible amount? | E35: INTEREST_RATE_60 | F35: Requested Product | G35: Numeric | H35: 0 | I35: Numeric | J35: 4 | K35: 2 | L35: 0 | M35: M | N35: O | O35: I | P35: I | Q35: I
A36: =+A35+1 -> 34 | B36: C3.Policy Rules.Decision Category | C36: Calculated by ID and sent to Core System | D36: C3.Policy Rules.Decision Category | E36: C3_DECISION_CATEGORY | F36: ID Output | H36: " " | I36: Alpha | J36: 20 | K36: 0 | L36: 0 | M36: ID | N36: O | Q36: O
A37: =+A36+1 -> 35 | B37: Upsell Flag | C37: Customer is eligible for upsel or not | D37: Upsell_Flag | E37: UPSELL_FLG | F37: ID Output | G37: Y/N | H37: " " | I37: Alpha | J37: 1 | K37: 0 | L37: 0 | M37: ID | N37: O | Q37: O
A38: =+A37+1 -> 36 | B38: App.Bureau Score | C38: For future use | E38: BUREAU_SCORE | F38: Individual Bureau | G38: Numeric | H38: 0 | I38: Numeric | J38: 4 | K38: 0 | L38: 0 | M38: C | N38: O | P38: I | Q38: I
A39: =+A38+1 -> 37 | B39: App.Total Non-Card Balance | C39: For future use | E39: TOTAL_NON_CARD_BALANCE | F39: Individual Bureau | G39: Numeric | H39: 0 | I39: Numeric | J39: 12 | K39: 0 | L39: 0 | M39: C | N39: O | P39: I | Q39: I
A40: =+A39+1 -> 38 | B40: App.Max Duration Since Opening of an Open Card | C40: For future use | E40: MAX_DUR_SINCE_CC_OPEN | F40: Individual Bureau | G40: Numeric | H40: 0 | I40: Numeric | J40: 4 | K40: 0 | L40: 0 | M40: C | N40: O | P40: I | Q40: I
A41: =+A40+1 -> 39 | B41: App.Bureau Investigation Date Since | C41: Duration since latest inquiry for customer in credit registry | D41: App.Bureau Investigation Date Since | E41: BUREAU_INVESTIGATION_DATE_SINCE | F41: Individual Bureau | G41: Numeric | H41: 0 | I41: Numeric | J41: 4 | K41: 0 | L41: 0 | M41: M | N41: O | P41: I | Q41: I
A42: =+A41+1 -> 40 | B42: App.Total Open Card Balance | C42: For future use | D42: App.Total Open Card Balance | E42: TOTAL_OPEN_CARD_BALANCE | F42: Individual Bureau | G42: Numeric | H42: 0 | I42: Numeric | J42: 12 | K42: 0 | L42: 0 | M42: C | N42: O | P42: I | Q42: I
A43: =+A42+1 -> 41 | B43: App.Percentage of Missed Payments | C43: For future use | E43: BUREAU_CARD_UTILIZATION | F43: Individual Bureau | G43: Numeric | H43: 0 | I43: Numeric | J43: 3 | K43: 3 | L43: 0 | M43: C | N43: O | P43: I | Q43: I
A44: =+A43+1 -> 42 | B44: App.30plus in Last Mo | C44: For future use | E44: LAST_MONTH_30 | F44: Individual Bureau | G44: Numeric | H44: 0 | I44: Numeric | J44: 4 | K44: 0 | L44: 0 | M44: C | N44: O | P44: I | Q44: I
A45: =+A44+1 -> 43 | B45: App.Total Charge Off Last 36M | C45: For future use | E45: NUM_CHARGE_OFF_36M | F45: Individual Bureau | G45: Numeric | H45: 0 | I45: Numeric | J45: 4 | K45: 0 | L45: 0 | M45: C | N45: O | P45: I | Q45: I
A46: =+A45+1 -> 44 | B46: App.WPS (Worst Payment Status) Ever | C46: For future use | D46: App.WPS (Worst Payment Status) Ever | E46: WPS_LIFETIME | F46: Individual Bureau | G46: Numeric | H46: 0 | I46: Numeric | J46: 1 | K46: 0 | L46: 0 | M46: C | N46: O | P46: I | Q46: I
A47: =+A46+1 -> 45 | B47: App.WPS Card Last 12M | C47: For future use | D47: App.WPS Card Last 12M | E47: IB_WPS_CARD_LAST_12M | F47: Individual Bureau | G47: Numeric | H47: 0 | I47: Numeric | J47: 4 | K47: 0 | L47: 0 | M47: C | N47: O | P47: I | Q47: I
A48: =+A47+1 -> 46 | B48: App.Total Loan Installment | C48: For future use | D48: App.Total Loan Installment | E48: TOTAL_LOAN_INSTALLMENT | F48: Individual Bureau | G48: Numeric | H48: 0 | I48: Numeric | J48: 12 | K48: 0 | L48: 0 | M48: C | N48: O | P48: I | Q48: I
A49: =+A48+1 -> 47 | B49: App.WPS Loan Last 12M | C49: For future use | D49: App.WPS Loan Last 12M | E49: IB_WPS_LOAN_LAST_12M | F49: Individual Bureau | G49: Numeric | H49: 0 | I49: Numeric | J49: 4 | K49: 0 | L49: 0 | M49: C | N49: O | P49: I | Q49: I
A50: =+A49+1 -> 48 | B50: App.WPS Mortgage Last 12M | C50: For future use | D50: App.WPS Mortgage Last 12M | E50: IB_WPS_MORTGAGE_LAST_12M | F50: Individual Bureau | G50: Numeric | H50: 0 | I50: Numeric | J50: 4 | K50: 0 | L50: 0 | M50: C | N50: O | P50: I | Q50: I
A51: =+A50+1 -> 49 | B51: App.WPS OD Last 12M | C51: For future use | D51: App.WPS OD Last 12M | E51: IB_WPS_OD_LAST_12M | F51: Individual Bureau | G51: Numeric | H51: 0 | I51: Numeric | J51: 4 | K51: 0 | L51: 0 | M51: C | N51: O | P51: I | Q51: I
A52: =+A51+1 -> 50 | B52: App.WPS Auto Loan Last 12M | C52: For future use | D52: App.WPS Auto Loan Last 12M | E52: IB_WPS_AUTO_LOAN_LAST_12M | F52: Individual Bureau | G52: Numeric | H52: 0 | I52: Numeric | J52: 4 | K52: 0 | L52: 0 | M52: C | N52: O | P52: I | Q52: I
A53: =+A52+1 -> 51 | B53: App.Existing customer flag | C53: If the applicant information is found to be a match with existing customer database of Bank, this flag should be Y | E53: EXISTING_CUSTOMER | F53: Internal Bureau | G53: Y/N | H53: N | I53: Alpha | J53: 1 | K53: 0 | L53: 0 | M53: M | N53: B | O53: I | P53: I | Q53: I
A54: =+A53+1 -> 52 | B54: App.Fraud List Flag | C54: Y if any match with existing fraud list | E54: Fraud_Flg (Credit_Bureau_Detail Table) | F54: Internal Bureau | G54: Y/N | H54: N | I54: Alpha | J54: 1 | K54: 0 | L54: 0 | M54: M | N54: B | O54: I | P54: I | Q54: I
A55: =+A54+1 -> 53 | B55: App.Behaviour Score | C55: Behavior score | E55: BEHAVIOUR_SCORE | F55: Internal Bureau | G55: Numeric | H55: 0 | I55: Numeric | J55: 4 | K55: 0 | L55: 0 | M55: M | N55: B | O55: I | P55: I | Q55: I
A56: =+A55+1 -> 54 | B56: App.Total Personal Loans Balance Unsecured | C56: Total loan balance of customer's existing noncollateralized loan accounts | E56: TOTAL_PERS_LOANS_BAL_UNSECURE | F56: Internal Bureau | G56: Numeric | H56: 0 | I56: Numeric | J56: 12 | K56: 0 | L56: 0 | M56: C | N56: B | O56: I | P56: I | Q56: I
A57: =+A56+1 -> 55 | B57: App.Declared Income | C57: Customer declared income | D57: Declared Income | E57: DECLARED_INCOME | F57: Individual Customer | G57: Numeric | H57: 0 | I57: Numeric | J57: 10 | K57: 0 | L57: 0 | M57: M | N57: O | O57: I | P57: I | Q57: I
A58: =+A57+1 -> 56 | B58: App.Declared Income fx | C58: Currency of the monthly net income | D58: Monthly income | E58: MONTHLY_INCOME_CURRENCY | F58: Individual Customer | H58: " " | I58: Alpha | J58: 2 | K58: 0 | L58: 0 | M58: M | N58: O | O58: I | P58: I | Q58: I
A59: =+A58+1 -> 57 | B59: App.Documented Income | C59: Income on the income document | D59: Applicant.Documented Income | E59: DOCUMENTED_INCOME | F59: Individual Customer | G59: Numeric | H59: 0 | I59: Numeric | J59: 10 | K59: 0 | L59: 0 | M59: M | N59: O | O59: I | P59: I | Q59: I
A60: =+A59+1 -> 58 | B60: App.Age | C60: Customer's age | D60: Age | E60: CUSTOMER_AGE | F60: Individual Customer | G60: Numeric | H60: 0 | I60: Numeric | J60: 3 | K60: 0 | L60: 0 | M60: C | N60: O | O60: I | P60: I | Q60: I
A61: =+A60+1 -> 59 | B61: App.Employment Type | C61: Customer's employment type | D61: App.Employment Type | E61: CUSTOMER_EMPLOYMENT_TYPE | F61: Individual Customer | G61: Pls. refer to "Parameters" sheet | H61: " " | I61: Alpha | J61: 1 | K61: 0 | L61: 0 | M61: M | N61: O | O61: I | P61: I | Q61: I
A62: =+A61+1 -> 60 | B62: App.Total Credit Cards Amount | C62: Total original card limit of customer's existing card accounts (open) | E62: TOTAL_CC_AMOUNT | F62: Internal Bureau | G62: Numeric | H62: 0 | I62: Numeric | J62: 12 | K62: 0 | L62: 0 | M62: C | N62: B | O62: I | P62: I | Q62: I
A63: =+A62+1 -> 61 | B63: App.Total Employment Duration | C63: Customer's total employment duration (in months) | D63: App.Total Employment Duration | E63: TOTAL_EMPLOYMENT_DURATION | F63: Individual Customer | G63: Numeric | H63: 0 | I63: Numeric | J63: 4 | K63: 0 | L63: 0 | M63: M | N63: O | O63: I | P63: I | Q63: I
A64: =+A63+1 -> 62 | B64: App.E-mail Flag | C64: Y if e-mail is entered in application | D64: App.E-mail Flag | E64: EMAIL_PROVIDED_FLG | F64: Individual Customer | G64: Y/N | H64: N | I64: Alpha | J64: 1 | K64: 0 | L64: 0 | M64: M | N64: O | O64: I | P64: I | Q64: I
A65: =+A64+1 -> 63 | B65: App.Total Overdrafts Amount | C65: Total original overdraft amount of customer's existing overdraft accounts (open) | E65: TOTAL_OVERDRAFTS_AMOUNT | F65: Internal Bureau | G65: Numeric | H65: 0 | I65: Numeric | J65: 12 | K65: 0 | L65: 0 | M65: C | N65: B | O65: I | P65: I | Q65: I
A66: =+A65+1 -> 64 | B66: App.Total Expenses | C66: Total monthly expenses of the customer declared in application form | D66: Customer Total Monthly Debt | E66: CUSTOMER_MONTHLY_EXPENCES | F66: Individual Customer | G66: Numeric | H66: 0 | I66: Numeric | J66: 10 | K66: 0 | L66: 0 | M66: M | N66: O | O66: I | P66: I | Q66: I
A67: =+A66+1 -> 65 | B67: Derived.Interest Rate | C67: Calculated by ID and sent to Core System | E67: INTEREST_RATE | F67: ID Output | G67: Numeric | H67: 0 | I67: Numeric | J67: 3 | K67: 3 | L67: 0 | M67: ID | N67: O | O67: O | P67: O | Q67: O
A68: =+A67+1 -> 66 | B68: App.Pledged Amount | C68: Core System will check if customer has a pledged account via HOLD_CODE and RECORD_STAT fields and will send the amount under pledge | D68: App.Pledged Amount | E68: PLEDGED_AMOUNT | F68: Individual Customer | G68: Numeric | H68: 0 | I68: Numeric | J68: 10 | K68: 0 | L68: 0 | M68: M | N68: O | O68: I | P68: I | Q68: I
A69: =+A68+1 -> 67 | B69: LPA.Min tenor | C69: Calculated by ID and sent to Core System | E69: MIN_TENOR | F69: ID Output | G69: Numeric | H69: 0 | I69: Numeric | J69: 5 | K69: 0 | L69: 0 | M69: ID | N69: O | O69: O | P69: O | Q69: O
A70: =+A69+1 -> 68 | B70: LPA.Max tenor | C70: Calculated by ID and sent to Core System | E70: MAX_TENOR | F70: ID Output | G70: Numeric | H70: 0 | I70: Numeric | J70: 5 | K70: 0 | L70: 0 | M70: ID | N70: O | O70: O | P70: O | Q70: O
A71: =+A70+1 -> 69 | B71: LPA.Min loan amount | C71: Calculated by ID and sent to Core System | E71: MIN_LOAN_AMOUNT | F71: ID Output | G71: Numeric | H71: 0 | I71: Numeric | J71: 7 | K71: 2 | L71: 0 | M71: ID | N71: O | O71: O | P71: O | Q71: O
A72: =+A71+1 -> 70 | B72: LPA.Max loan amount | C72: Calculated by ID and sent to Core System | E72: MAX_LOAN_AMOUNT | F72: ID Output | G72: Numeric | H72: 0 | I72: Numeric | J72: 7 | K72: 2 | L72: 0 | M72: ID | N72: O | O72: O | P72: O | Q72: O
A73: =+A72+1 -> 71 | B73: App.Application.Staff | C73: Flag to show if customer is bank's staff | D73: App.Application.Staff | E73: IS_EMPLOYEE_FLG | F73: Individual Customer | G73: Y/N | H73: N | I73: Alpha | J73: 1 | K73: 0 | L73: 0 | M73: M | N73: O | O73: I | P73: I | Q73: I
A74: =+A73+1 -> 72 | B74: App.Customer status | C74: Customers' all existing accounts with Bank are searched and final status decision is flagged in this field as per valid values definition | D74: App.Customer status | E74: CUSTOMER_STATUS | F74: Internal Bureau | G74: If customer has any acount under legal follow up L,S,W,A,R,V, if customer has open credit account with Bank O, if all accounts are closed C. | H74: " " | I74: Alpha | J74: 1 | K74: 0 | L74: 0 | M74: M | N74: B | O74: I | P74: I | Q74: I
A75: =+A74+1 -> 73 | B75: App.Total Open personal loans Installment | C75: Total installment amount of open loan accounts | D75: App.Total Open Loans Installment | E75: TOTAL_OPEN_LOAN_INSTALLMENT | F75: Internal Bureau | G75: Numeric | H75: 0 | I75: Numeric | J75: 12 | K75: 0 | L75: 0 | M75: C | N75: B | O75: I | P75: I | Q75: I
A76: =+A75+1 -> 74 | B76: App.Current 30 dpd number of personal loans | C76: Number of open loans with 31-60 dpd | D76: App.Current 30 dpd number of personal loans | E76: DPD30_PERSONAL_LOANS_CNT | F76: Internal Bureau | G76: Numeric | H76: 0 | I76: Numeric | J76: 4 | K76: 0 | L76: 0 | M76: C | N76: B | O76: I | P76: I | Q76: I
A77: =+A76+1 -> 75 | B77: App.Current 30 dpd number of Mortgage loans | C77: Number of open loans with 31-60 dpd | D77: App.Current 30 dpd number of Mortgage loans | E77: DPD30_MORTGAGE_LOANS_CNT | F77: Internal Bureau | G77: Numeric | H77: 0 | I77: Numeric | J77: 4 | K77: 0 | L77: 0 | M77: C | N77: B | O77: I | P77: I | Q77: I
A78: =+A77+1 -> 76 | B78: App.Current 30 dpd number of Auto loans | C78: Number of open loans with 31-60 dpd | D78: App.Current 30 dpd number of Auto loans | E78: DPD30_AUTO_LOANS_CNT | F78: Internal Bureau | G78: Numeric | H78: 0 | I78: Numeric | J78: 4 | K78: 0 | L78: 0 | M78: C | N78: B | O78: I | P78: I | Q78: I
A79: =+A78+1 -> 77 | B79: App.Total Open Credit Cards Balance | C79: Total outstanding balance of open card accounts | D79: App.Total Open Credit Cards Balance | E79: TOTAL_OPEN_CC_BALANCE | F79: Internal Bureau | G79: Numeric | H79: 0 | I79: Numeric | J79: 12 | K79: 0 | L79: 0 | M79: C | N79: B | O79: I | P79: I | Q79: I
A80: =+A79+1 -> 78 | B80: C1.Policy Rules.Sorted Reason Codes | C80: Calculated by ID and sent to Core System | E80: C1_REASON_CODES | F80: ID Output | H80: " " | I80: Alpha | J80: 4 | K80: 0 | L80: 10 | M80: ID | N80: O | O80: O
A81: =+A80+1 -> 79 | B81: CB Decision.Applicant.Flag | C81: ID's decision on asking for fresh credit bureau (for future use) | E81: CALL_BUREAU | F81: ID Output | G81: Y/N | H81: " " | I81: Alpha | J81: 1 | K81: 0 | L81: 0 | M81: ID | N81: O | O81: O
A82: =+A81+1 -> 80 | B82: App.Current 30 dpd number of Credit Cards | C82: Number of open cards with 31-60 dpd | D82: App.Current 30 dpd number of Credit Cards | E82: DPD30_CC_LOANS_CNT | F82: Internal Bureau | G82: Numeric | H82: 0 | I82: Numeric | J82: 4 | K82: 0 | L82: 0 | M82: C | N82: B | O82: I | P82: I | Q82: I
A83: =+A82+1 -> 81 | B83: App.Current 30 dpd number of Overdrafts | C83: Number of open Overdrafts with 31-60 dpd | D83: App.Current 30 dpd number of Overdrafts | E83: DPD30_OVERDRAFT_LOANS_CNT | F83: Internal Bureau | G83: Numeric | H83: 0 | I83: Numeric | J83: 4 | K83: 0 | L83: 0 | M83: C | N83: B | O83: I | P83: I | Q83: I
A84: =+A83+1 -> 82 | B84: Requested Loan Amount | C84: Requested Loan Amount / card limit | D84: Requested Loan Amount | E84: REQUESTED_LOAN_AMOUNT | F84: Requested Product | G84: Numeric | H84: 0 | I84: Numeric | J84: 10 | K84: 0 | L84: 0 | M84: M | N84: O | O84: I | P84: I | Q84: I
A85: =+A84+1 -> 83 | B85: Requested Product Code | C85: Product code in Core System used to identify each specific product which holds all the product information such as pricing and other T&C | D85: Product code | E85: PRODUCT_CODE | F85: Requested Product | G85: Core System Product codes | H85: " " | I85: Alpha | J85: 3 | K85: 0 | L85: 0 | M85: M | N85: O | O85: I | P85: I | Q85: I
A86: =+A85+1 -> 84 | B86: Decision.Decision Category | C86: Calculated by ID and sent to Core System | E86: DECISION_CATEGORY | F86: ID Output | H86: " " | I86: Alpha | J86: 20 | K86: 0 | L86: 0 | M86: ID | N86: O | Q86: O
A87: =+A86+1 -> 85 | B87: Requested Payment Plan Type | C87: Requested payment plan type (equal monthly, baloon, skip, flexible..etc) | D87: Requested Payment Plan Type | E87: REQUESTED_PAYMENT_PLAN | F87: Requested Product | G87: Pls. refer to "Parameters" sheet | H87: " " | I87: Alpha | J87: 1 | K87: 0 | L87: 0 | M87: M | N87: O | O87: I | P87: I | Q87: I
A88: =+A87+1 -> 86 | B88: Approver Level | C88: Calculated by ID and sent to Core System | F88: ID Output | G88: Pls. refer to "Parameters" sheet | H88: " " | I88: Alpha | J88: 2 | K88: 0 | L88: 0 | M88: ID | N88: O | Q88: O
A89: =+A88+1 -> 87 | B89: Verification Decision.Decision | C89: Calculated by ID and sent to Core System | E89: VERIFICATION_DECISION_FLG | F89: ID Output | G89: Y/N
A90: =+A89+1 -> 88 | B90: Verification Complete
A91: =+A90+1 -> 89 | B91: Documentation Complete Flag | E91: DOCUMENTATION_COMPLETED_FLG | F91: ID Input | G91: Y/N | H91: " " | I91: Alpha
A92: =+A91+1 -> 90 | B92: email inconsistency flag
A93: =+A92+1 -> 91 | B93: Customer Total Monthly Debt | C93: Derived Customer Total Monthly Debt | E93: CUSTOMER_TOTAL_MONTHLY_DEBT | F93: Individual Customer | G93: Numeric | H93: 0 | I93: Numeric | J93: 10 | K93: 0 | L93: 0 | M93: M | N93: O | O93: O | P93: I | Q93: I
A94: =+A93+1 -> 92 | B94: App.Verified Income | C94: App.Verified Income (From Zeynep 02.03.2023) | D94: Verified Income | E94: VERIFIED_INCOME | F94: Individual Customer | G94: Numeric | H94: 0 | I94: Numeric | J94: 10 | K94: 0 | L94: 0 | M94: M | N94: O | O94: I | P94: I | Q94: I
A95: =+A94+1 -> 93 | B95: DOCUMENTATION_TYPE | C95: For rule // Determines if a documentation is required | E95: DOCUMENTATION_TYPE | G95: "SC"
A96: =+A95+1 -> 94 | B96: DOCUMENTATION.DECISION | E96: DOCUMENTATION_DECISION_FLG | F96: ID Output | G96: Y/N
A97: =+A96+1 -> 95 | B97: INTEREST_INCOME | E97: INTEREST_INCOME | F97: ID Input
A98: =+A97+1 -> 96 | B98: DPD30_CASH_COLLATERAL_CNT | E98: DPD30_CASH_COLLATERAL_CNT | F98: ID Input
A99: =+A98+1 -> 97 | B99: HOME_INCONSISTENCY_FLG | C99: If Home city inconsistency flag for main applicant = Y OR Business/work city inconsistency flag for main applicant = Y OR Email inconsistency flag for main applicant = Y OR Mother's maiden name inconsistency flag for main applicant = Y | E99: HOME_INCONSISTENCY_FLG | F99: ID Input | G99: Y/N
A100: =+A99+1 -> 98 | B100: BUSINESS_INCONSISTENCY_FLG | C100: If Home city inconsistency flag for main applicant = Y OR Business/work city inconsistency flag for main applicant = Y OR Email inconsistency flag for main applicant = Y OR Mother's maiden name inconsistency flag for main applicant = Y | E100: BUSINESS_INCONSISTENCY_FLG | F100: ID Input | G100: Y/N
...

Sheet Parameters
A1: DD Name | B1: Channel | D1: City | F1: ID non-confirmation reason | H1: Other Income Type | J1: Country/ Nationality | L1: Education | N1: Employment Type | P1: Gender | R1: Marital Status | T1: Occupation | V1: Residence Type | X1: Payment Plan Type | Z1: Product Type | AB1: Risk Segmentation.Risk Segment | AD1: Currency | AF1: ID Type | AH1: WORK POSITION | AJ1: RESIDENCY | AL1: Loan Purpose | AN1: Credit Registry Status Fields
A2: # | B2: Possible Values | C2: Code | D2: Possible Values | E2: Code | F2: Possible Values | G2: Code | H2: Possible Values | I2: Code | J2: Possible Values | K2: Code | L2: Possible Values | M2: Code | N2: Possible Values | O2: Code | P2: Possible Values | Q2: Code | R2: Possible Values | S2: Code | T2: Possible Values | U2: Code | V2: Possible Values | W2: Code | X2: Possible Values | Y2: Code | Z2: Possible Values | AA2: Code | AB2: Code | AC2: Core System Value | AD2: Possible Values | AE2: Code | AF2: Possible Values | AG2: Code | AH2: Possible Values | AI2: Code | AJ2: Possible Values | AK2: Code | AL2: Possible Values | AM2: Code | AN2: Possible Values | AO2: Description
A3: 1 | B3: Branches | C3: BR | F3: System issues | G3: 01 | H3: Rent | I3: R | J3: Afganistan | K3: AF | L3: Primary | M3: P | N3: Unemployed | O3: U | P3: Male | Q3: M | R3: Married | S3: M | T3: AGENT - BROKER | U3: 01 | V3: Belongs to family | W3: F | X3: Equal monthly | Y3: E | Z3: Super Loan | AA3: SL | AB3: VL | AC3: Very low risk | AD3: ALL | AE3: 01 | AF3: Citizen ID | AG3: 1 | AH3: Owner/Partner | AI3: P | AJ3: Citizen | AK3: 1 | AL3: Home Loan | AM3: 1 | AN3: 0 | AO3: current
A4: 2 | B4: Direct Sales | C4: DS | F4: No ID document | G4: 02 | H4: Retirement | I4: E | J4: Almanya | K4: DE | L4: Doctorate | M4: D | N4: Retired | O4: R | P4: Female | Q4: F | R4: Single | S4: S | T4: AGRONOMIST | U4: 02 | V4: Belongs to someone else | W4: S | X4: Grace Period | Y4: S | Z4: Pensioner Loan | AA4: PL | AB4: LO | AC4: Low Risk | AD4: USD | AE4: 02 | AF4: Driving Licence | AG4: 2 | AH4: Top Manager | AI4: E | AJ4: Resident Permit Holder | AK4: 2 | AL4: House Contruction | AM4: 2 | AN4: 1,2,3 | AO4: delinquent
A5: 3 | B5: Website | C5: IN | H5: Spouse salary | I5: H | J5: Amerika Birleşik Devletleri | K5: US | L5: High School | M5: H | N5: Public Sector salaried | O5: P | R5: Divorced | S5: D | T5: ARCHAEOLOGIST | U5: 03 | V5: Belongs to customer | W5: C | X5: Interim payments | Y5: I | Z5: Home Loan | AA5: HL | AB5: ME | AC5: Medium Risk | AD5: CHF | AE5: 07 | AF5: Passport | AG5: 3 | AH5: Manager( up to Top Manager) | AI5: S | AJ5: Immigrant | AK5: 3 | AL5: Shop Loan | AM5: 3 | AN5: 4 | AO5: Legal
A6: 4 | B6: Call Center | C6: CC | H6: Family company share | I6: F | J6: Amerikan Samoa | K6: AS | L6: Masters | M6: M | N6: Private Sector salaried | O6: S | R6: Widowed | S6: W | T6: ARCHITECT - DESIGNER | U6: 04 | V6: Rent | W6: R | X6: Increasing payments | Y6: P | Z6: House Contruction | AA6: HC | AB6: HI | AC6: High Risj | AD6: CAD | AE6: 08 | AH6: Manager | AI6: M | AJ6: Non Resident | AK6: 4 | AL6: Home Improvement | AM6: 4 | AN6: 5 | AO6: closed
A7: 5 | B7: SMS | C7: SM | H7: Social Aid | I7: S | J7: Andorra | K7: AD | L7: University/College | M7: U | N7: Physical Person | O7: E | R7: Engaged/Co-Living | S7: E | T7: ARTIST | U7: 05 | V7: Co-Owner | W7: N | X7: Baloon payments | Y7: B | Z7: Shop Loan | AA7: SC | AB7: VH | AC7: Very High Risk | AD7: KWD | AE7: 09 | AH7: Officer (up to manager) | AI7: F | AL7: Health | AM7: 5 | AN7: 6 | AO7: write-off
A8: 6 | B8: eBanking | C8: EB | H8: Agriculture Income | I8: A | J8: Angola | K8: AO | N8: Housewife | O8: H | T8: LAWYER | U8: 06 | V8: Mortgage | W8: M | X8: Equal principal | Y8: Z | Z8: Home Improvement | AA8: HI | AD8: GBP | AE8: 10 | AH8: Laborer | AI8: L | AL8: Education | AM8: 6 | AN8: 7 | AO8: reversed
A9: 7 | B9: Mobile | C9: MB | H9: Remittance | I9: M | J9: Anguila | K9: AV | N9: Student | O9: T | T9: BANKER | U9: 07 | V9: Other | W9: O | X9: Flexible | Y9: F | Z9: Health | AA9: HT | AD9: SAR | AE9: 05 | AH9: Other | AI9: O | AL9: Turism | AM9: 7
A10: 8 | B10: ATM | C10: AT | H10: Military Pension | I10: P | J10: Anguilla | K10: AI | N10: Self-employed Professional | O10: L | T10: DEPUTY | U10: 08 | X10: Quarterly | Y10: 3 | Z10: Education | AA10: ED | AD10: JPY | AE10: 06 | AL10: Wedding | AM10: 8
A11: 9 | B11: Merchant | C11: ME | H11: Divorced Pension | I11: D | J11: Antarktika | K11: AQ | N11: Owner/Shareholder | O11: O | T11: DOCTOR | U11: 09 | X11: Semi-annually | Y11: 6 | Z11: Consumer Durable | AA11: CD | AD11: EUR | AE11: 03 | AL11: Land purchase | AM11: 9
A12: 10 | B12: Agent | C12: AG | H12: Health Pension | I12: L | J12: Antigua ve Barbuda | K12: AG | N12: Farmer | O12: F | T12: GENERAL DIRECTOR OF PUBLIC INSTITUTION | U12: 10 | X12: Bullet Payment | Y12: U | Z12: Technical Equipment | AA12: TE | AD12: AUD | AE12: 11 | AL12: Financial investment | AM12: 10
A13: 11 | H13: Honoraries & Bonuses | I13: B | J13: Arjantin | K13: AR | N13: NGO/ NPO (Non-government/Non-profit) | O13: N | T13: ECONOMIST | U13: 11 | Z13: Used Car | AA13: UC | AD13: IRR | AE13: 12 | AL13: State payments | AM13: 11
A14: 12 | H14: Other | I14: O | J14: Arnavutluk | K14: AL | N14: Immigrant | O14: M | T14: PHARMACIST | U14: 12 | Z14: New Car | AA14: NC | AD14: DKK | AE14: 13 | AL14: Consumer electronic | AM14: 12
A15: 13 | J15: Aruba | K15: AW | N15: Banking / Financial Institution salaried | O15: B | T15: FARMER | U15: 13 | Z15: Overdraft | AA15: OD | AD15: SEK | AE15: 14 | AL15: House Furnishing | AM15: 13
A16: 14 | J16: Ascention Adaları | K16: AC | T16: JOURNALIST | U16: 14 | Z16: Credit Card | AA16: CC | AD16: AED | AE16: 04 | AL16: Debt Purchase | AM16: 14
A17: 15 | J17: Avustralya | K17: AU | T17: GEOLOGIST | U17: 15 | Z17: Cash Collateral | AA17: CL | AD17: TRY | AE17: 15 | AL17: Technical Equipment | AM17: 15
A18: 16 | J18: Avusturya | K18: AT | T18: JUDGE | U18: 16 | Z18: Business Credit Card | AA18: BC | AL18: Used Car | AM18: 16
A19: 17 | J19: Azerbaycan | K19: AZ | T19: UNEMPLOYED | U19: 17 | Z19: Investment Loan | AA19: IL | AL19: New Car | AM19: 17
A20: 18 | J20: Bahama | K20: BS | T20: SELF-EMPLOYED | U20: 18 | Z20: Agro Loan | AA20: AL | AL20: Investment Loan | AM20: 18
A21: 19 | J21: Bahreyn | K21: BH | T21: INDUSTRIALIST | U21: 19 | Z21: Startup Loan | AA21: SU | AL21: Agro Loan | AM21: 19
A22: 20 | J22: Bangladeş | K22: BD | T22: NURSE | U22: 20 | Z22: Revolving Line | AA22: RL | AL22: Startup Loan | AM22: 20
A23: 21 | J23: Barbados | K23: BB | T23: INSPECTOR | U23: 21 | Z23: Inventory Loan | AA23: IV | AL23: Inventory Loan | AM23: 21
A24: 22 | J24: Batı Sahra | K24: EH | T24: ENGINEER | U24: 22 | Z24: Letter of Guarantee | AA24: LG | AL24: Consumer Refinance | AM24: 22
A25: 23 | J25: Belçika | K25: BE | T25: LAWYER | U25: 23 | Z25: Letter of Credit | AA25: LC
A26: 24 | J26: Belize | K26: BZ | T26: ACCOUNTANT | U26: 24 | Z26: Cheque Collateralized | AA26: CH
A27: 25 | J27: Benin | K27: BJ | T27: MATHEMATICIAN - PHYSICIST | U27: 25 | Z27: …
A28: 26 | J28: Bermuda | K28: BM | T28: MANAGER | U28: 26 | Z28: Staff Loan GPSL | AA28: EL
A29: 27 | J29: Beyaz Rusya (Belarus) | K29: BY | T29: EDUCATION STAFF | U29: 27 | Z29: Staff Loan SRCP/GPSL | AA29: ES
A30: 28 | J30: Bhutan | K30: BT | T30: MINORS | U30: 28 | Z30: Staff Loan HOME Loan | AA30: EH
A31: 29 | J31: Birleşik Arap Emirlikleri | K31: AE | T31: MASTER, CRAFT | U31: 29 | Z31: Staff Loan HOME Loan SRCP | AA31: ER
A32: 30 | J32: Birleşik Krallık | K32: UK | T32: EMPLOYEE(STATE) | U32: 30 | Z32: Consumer Refinance | AA32: CR
A33: 31 | J33: Bolivya | K33: BO | T33: HEALTH STAFF | U33: 31
A34: 32 | J34: Bosna Hersek | K34: BA | T34: EMPLOYEE(PRIVATE) | U34: 32
A35: 33 | J35: Botsvana | K35: BW | T35: NOTARY | U35: 33
A36: 34 | J36: Bouvet Adası | K36: BV | T36: MILLITARY STAFF | U36: 34
A37: 35 | J37: Brezilya | K37: BR | T37: TOURIST OPERATOR | U37: 35
A38: 36 | J38: Britanya Hint Okyanusu Toprağı | K38: IO | T38: LECTURER | U38: 36
A39: 37 | J39: Brunei Darüsselam | K39: BN | T39: RETIREE | U39: 37
A40: 38 | J40: Bulgaristan | K40: BG | T40: POLICE OFFICER | U40: 38
A41: 39 | J41: Burkina Faso | K41: BF | T41: PHYCOLOGIST | U41: 39
A42: 40 | J42: Burundi | K42: BI | T42: WORKER | U42: 40
A43: 41 | J43: Büyük Britanya (UK) | K43: GB | T43: SOCIAL WORKER | U43: 41
A44: 42 | J44: Cebelitarık | K44: GI | T44: IT DEVELOPER – IT OFFICER | U44: 42
... A53: 51 | J53: Çin | K53: CN | T53: VETERINARY | U53: 51
A54: 52 | J54: Danimarka | K54: DK
A55: 53 | J55: Doğu Timor | K55: TP
A56: 54 | J56: Dominik Cumhuriyeti | K56: DO
A57: 55 | J57: Dominika | K57: DM
A58: 56 | J58: Ekvador | K58: EC
A59: 57 | J59: Ekvator Ginesi | K59: GQ
A60: 58 | J60: El Salvador | K60: SV
A61: 59 | J61: Endonezya | K61: ID
A62: 60 | J62: Eritre | K62: ER
A63: 61 | J63: Ermenistan | K63: AM
A64: 62 | J64: Estonya | K64: EE
A65: 63 | J65: Etiyopya | K65: ET
... A175: 173 | J175: Panama | K175: PA
J176: Papua Yeni Gine | K176: PG
J177: Paraguay | K177: PY
J178: Peru | K178: PE
J179: Pitcairn | K179: PN
J180: Polonya | K180: PL
J181: Portekiz | K181: PT
J182: Portoriko | K182: PR
J183: Reunion | K183: RE
J184: Romanya | K184: RO
J185: Ruanda | K185: RW
J186: Rusya Federasyonu | K186: RU
J187: S. Georgia ve S. Sandwich Adaları | K187: GS
... J248: Zimbabve | K248: ZW

Sheet synthetic.py
A1: NAME | B1: FORMAT | C1: xLookup(Data Dictionary All) | D1: oculaires
A2: RANDOM_ID | B2: str(uuid.uuid4()) | C2: =_xlfn.XLOOKUP(A2,'Data Dictionary_All'!$E$1:$E$871,'Data Dictionary_All'!$E$1:$E$871,"n/a",0) -> RANDOM_ID | D2: 1
A3: CUSTOMER_RK | B3: i | C3: =_xlfn.XLOOKUP(A3,'Data Dictionary_All'!$E$1:$E$873,'Data Dictionary_All'!$E$1:$E$873,"n/a",0) -> n/a | D3: 0
A4: NAME | B4: fake.name() | C4: =_xlfn.XLOOKUP(A4,'Data Dictionary_All'!$E$1:$E$873,'Data Dictionary_All'!$E$1:$E$873,"n/a",1) -> NUM_CHARGE_OFF_36M | D4: 0
A5: ADDRESS | B5: fake.address().replace("\n", " ") | C5: =_xlfn.XLOOKUP(A5,'Data Dictionary_All'!$E$1:$E$873,'Data Dictionary_All'!$E$1:$E$873,"n/a",1) -> BEHAVIOUR_SCORE | D5: 0
A6: PHONE | B6: fake.phone_number() | C6: =_xlfn.XLOOKUP(A6,'Data Dictionary_All'!$E$1:$E$873,'Data Dictionary_All'!$E$1:$E$873,"n/a",1) -> PLEDGED_AMOUNT | D6: 0
A7: EMAIL | B7: fake.email() | C7: =_xlfn.XLOOKUP(A7,'Data Dictionary_All'!$E$1:$E$873,'Data Dictionary_All'!$E$1:$E$873,"n/a",1) -> EMAIL_INCONSISTENCY_FLG | D7: 0
A8: PERMANENT_RESIDENCE_FLG | B8: generate_flag(0.97) | C8: =_xlfn.XLOOKUP(A8,'Data Dictionary_All'!$E$1:$E$873,'Data Dictionary_All'!$E$1:$E$873,"n/a",1) -> PERMANENT_RESIDENT_FLG | D8: 1
A9: CUSTOMER_AGE | B9: generate_customer_age() | C9: =_xlfn.XLOOKUP(A9,'Data Dictionary_All'!$E$1:$E$873,'Data Dictionary_All'!$E$1:$E$873,"n/a",1) -> CUSTOMER_AGE | D9: 1
A10: CUSTOMER_STATUS | B10: generate_customer_status() | C10: =_xlfn.XLOOKUP(A10,'Data Dictionary_All'!$E$1:$E$873,'Data Dictionary_All'!$E$1:$E$873,"n/a",1) -> CUSTOMER_STATUS | D10: 1
A11: BUREAU_SCORE | B11: random.randint(601, 850) if random.random() < 0.6 else random.randint(250, 600) | C11: =_xlfn.XLOOKUP(A11,'Data Dictionary_All'!$E$1:$E$873,'Data Dictionary_All'!$E$1:$E$873,"n/a",1) -> BUREAU_SCORE | D11: 1
A12: TOTAL_NON_CARD_BALANCE | B12: random.randint(0, 50000) | C12: =_xlfn.XLOOKUP(A12,'Data Dictionary_All'!$E$1:$E$873,'Data Dictionary_All'!$E$1:$E$873,"n/a",1) -> TOTAL_NON_CARD_BALANCE | D12: 1
A13: BUREAU_INVESTIGATION_DATE_SINCE | B13: random.randint(0, 90) | C13: =_xlfn.XLOOKUP(A13,'Data Dictionary_All'!$E$1:$E$873,'Data Dictionary_All'!$E$1:$E$873,"n/a",1) -> BUREAU_INVESTIGATION_DATE_SINCE | D13: 1
A14: BUREAU_CARD_UTILIZATION | B14: round(random.uniform(0.0, 1.0), 2) | C14: =_xlfn.XLOOKUP(A14,'Data Dictionary_All'!$E$1:$E$873,'Data Dictionary_All'!$E$1:$E$873,"n/a",1) -> BUREAU_CARD_UTILIZATION | D14: 1
A15: DOCUMENTATION_COMPLETED_FLG | B15: generate_documentation_completed_flag(call_id) | C15: =_xlfn.XLOOKUP(A15,'Data Dictionary_All'!$E$1:$E$873,'Data Dictionary_All'!$E$1:$E$873,"n/a",1) -> DOCUMENTATION_COMPLETED_FLG | D15: 1
... A55: EMAIL_INCONSISTENCY_FLG | B55: generate_flag(0.02) | C55: =_xlfn.XLOOKUP(A55,'Data Dictionary_All'!$E$1:$E$873,'Data Dictionary_All'!$E$1:$E$873,"n/a",1) -> EMAIL_INCONSISTENCY_FLG | D55: 1
A56: IS_EMPLOYEE_FLG | B56: generate_flag(0.5), # 50% Y50% N | C56: =_xlfn.XLOOKUP(A56,'Data Dictionary_All'!$E$1:$E$873,'Data Dictionary_All'!$E$1:$E$873,"n/a",0) -> IS_EMPLOYEE_FLG | D56: 1
A57: DECLARED_INCOME | B57: random.randint(3000, 15000) | C57: =_xlfn.XLOOKUP(A57,'Data Dictionary_All'!$E$1:$E$873,'Data Dictionary_All'!$E$1:$E$873,"n/a",1) -> DECLARED_INCOME | D57: 1
A58: DOCUMENTED_INCOME | B58: documented_income | C58: =_xlfn.XLOOKUP(A58,'Data Dictionary_All'!$E$1:$E$873,'Data Dictionary_All'!$E$1:$E$873,"n/a",1) -> DOCUMENTED_INCOME | D58: 1
A59: TOTAL_EMPLOYMENT_DURATION | B59: random.randint(6, 240)in months | C59: =_xlfn.XLOOKUP(A59,'Data Dictionary_All'!$E$1:$E$873,'Data Dictionary_All'!$E$1:$E$873,"n/a",1) -> TOTAL_EMPLOYMENT_DURATION | D59: 1
A60: PLEDGED_AMOUNT | B60: generate_pledged_amount() | C60: =_xlfn.XLOOKUP(A60,'Data Dictionary_All'!$E$1:$E$873,'Data Dictionary_All'!$E$1:$E$873,"n/a",1) -> PLEDGED_AMOUNT | D60: 1
A61: VERIFIED_INCOME | B61: verified_income | C61: =_xlfn.XLOOKUP(A61,'Data Dictionary_All'!$E$1:$E$873,'Data Dictionary_All'!$E$1:$E$873,"n/a",1) -> VERIFIED_INCOME | D61: 1
A62: WPS_LIFETIME | B62: generate_wps_lifetime() | C62: =_xlfn.XLOOKUP(A62,'Data Dictionary_All'!$E$1:$E$873,'Data Dictionary_All'!$E$1:$E$873,"n/a",1) -> WPS_LIFETIME | D62: 1
A63: CUSTOMER_MONTHLY_EXPENSES | B63: customer_monthly_expenses | C63: =_xlfn.XLOOKUP(A63,'Data Dictionary_All'!$E$1:$E$873,'Data Dictionary_All'!$E$1:$E$873,"n/a",1) -> CUSTOMER_STATUS | D63: 0
A64: CALL_ID | B64: call_id | C64: =_xlfn.XLOOKUP(A64,'Data Dictionary_All'!$E$1:$E$873,'Data Dictionary_All'!$E$1:$E$873,"n/a",1) -> CALL_ID | D64: 1
A65: BAD | B65: generate_bad_flag()Only 6% bad customers | C65: =_xlfn.XLOOKUP(A65,'Data Dictionary_All'!$E$1:$E$873,'Data Dictionary_All'!$E$1:$E$873,"n/a",1) -> BEHAVIOUR_SCORE | D65: 0
